Workbook

Sheet Weighting Reg Results
A1: SUMMARY OUTPUT
A3: Regression Statistics
A4: Multiple R | B4: 0.94322725
A5: R Square | B5: 0.88967764
A6: Adjusted R Square | B6: 0.85624663
A7: Standard Error | B7: 10944.402
A8: Observations | B8: 44
A10: ANOVA
B11: df | C11: SS | D11: MS | E11: F | F11: Significance F
A12: Regression | B12: 10 | C12: 3.1876245e+10 | D12: 3.1876245e+09 | E12: 26.612342 | F12: 5.5596547e-13
A13: Residual | B13: 33 | C13: 3.9527378e+09 | D13: 1.1977993e+08
A14: Total | B14: 43 | C14: 3.5828983e+10
B16: Coefficients | C16: Standard Error | D16: t Stat | E16: P-value | F16: Lower 95% | G16: Upper 95% | H16: Lower 95.0% | I16: Upper 95.0%
A17: Intercept | B17: -22748.9 | C17: 10804.037 | D17: -2.1055926 | E17: 0.042932352 | F17: -44729.879 | G17: -767.92178 | H17: -44729.879 | I17: -767.92178
A18: Education | B18: 2269.2016 | C18: 2850.26 | D18: 0.79613843 | E18: 0.4316418 | F18: -3529.6961 | G18: 8068.0992 | H18: -3529.6961 | I18: 8068.0992
A19: Experience | B19: 4356.0717 | C19: 2213.2026 | D19: 1.968221 | E19: 0.057491241 | F19: -146.72277 | G19: 8858.8662 | H19: -146.72277 | I19: 8858.8662
A20: Purpose of Contacts | B20: 1338.1545 | C20: 2824.3812 | D20: 0.4737868 | E20: 0.63877163 | F20: -4408.0922 | G20: 7084.4013 | H20: -4408.0922 | I20: 7084.4013
A21: Decision Making | B21: 6479.9513 | C21: 3784.4607 | D21: 1.7122522 | E21: 0.096233705 | F21: -1219.5919 | G21: 14179.494 | H21: -1219.5919 | I21: 14179.494
A22: Accountability | B22: -12070.15 | C22: 3419.7159 | D22: -3.5295769 | E22: 0.0012502453 | F22: -19027.615 | G22: -5112.6861 | H22: -19027.615 | I22: -5112.6861
A23: Contract Management | B23: 3045.7428 | C23: 2676.5953 | D23: 1.1379168 | E23: 0.26334969 | F23: -2399.8313 | G23: 8491.3169 | H23: -2399.8313 | I23: 8491.3169
A24: Budget | B24: 16736.869 | C24: 4421.591 | D24: 3.7852594 | E24: 0.00061624833 | F24: 7741.0744 | G24: 25732.663 | H24: 7741.0744 | I24: 25732.663
A25: Customer Service | B25: 6337.8495 | C25: 2640.9486 | D25: 2.3998383 | E25: 0.022204558 | F25: 964.79926 | G25: 11710.9 | H25: 964.79926 | I25: 11710.9
A26: Working Conditions | B26: 9503.7582 | C26: 3167.0283 | D26: 3.0008441 | E26: 0.0050960439 | F26: 3060.3907 | G26: 15947.126 | H26: 3060.3907 | I26: 15947.126
A27: Work Demands | B27: 7376.0292 | C27: 3267.5312 | D27: 2.2573707 | E27: 0.030725581 | F27: 728.18699 | G27: 14023.871 | H27: 728.18699 | I27: 14023.871

Sheet Points Schedule
H1: Points Schedule
B2: CFs | C2: Coefficients | D2: Weight | E2: Degree Levels | F2: Points | G2: Degree Level: | H2: 1 | I2: 2 | J2: 3 | K2: 4 | L2: 5 | M2: 6
B3: Education | C3: 2269.2016 | D3: =C3/$C$13 -> 0.039503103 | E3: 5 | F3: =1000*D3/E3 -> 7.9006206 | H3: 10 | I3: =H3+$H$3 -> 20 | J3: =I3+$H$3 -> 30 | K3: =J3+$H$3 -> 40 | L3: =K3+$H$3 -> 50
B4: Experience | C4: 4356.0717 | D4: =C4/$C$13 -> 0.075832114 | E4: 6 | F4: =1000*D4/E4 -> 12.638686 | H4: 15 | I4: =H4+$H$4 -> 30 | J4: =I4+$H$4 -> 45 | K4: =J4+$H$4 -> 60 | L4: =K4+$H$4 -> 75 | M4: =L4+$H$4 -> 90
B5: Purpose of Contacts | C5: 1338.1545 | D5: =C5/$C$13 -> 0.023295091 | E5: 6 | F5: =1000*D5/E5 -> 3.8825151 | H5: 5 | I5: =H5+$H$5 -> 10 | J5: =I5+$H$5 -> 15 | K5: =J5+$H$5 -> 20 | L5: =K5+$H$5 -> 25 | M5: =L5+$H$5 -> 30
B6: Decision Making | C6: 6479.9513 | D6: =C6/$C$13 -> 0.1128054 | E6: 5 | F6: =1000*D6/E6 -> 22.561079 | H6: 25 | I6: =H6+$H$6 -> 50 | J6: =I6+$H$6 -> 75 | K6: =J6+$H$6 -> 100 | L6: =K6+$H$6 -> 125
B7: Contract Management | C7: 3045.7428 | D7: =C7/$C$13 -> 0.053021422 | E7: 5 | F7: =1000*D7/E7 -> 10.604284 | H7: 10 | I7: =H7+$H$7 -> 20 | J7: =I7+$H$7 -> 30 | K7: =J7+$H$7 -> 40 | L7: =K7+$H$7 -> 50
B8: Budget | C8: 16736.869 | D8: =C8/$C$13 -> 0.29136163 | E8: 4 | F8: =1000*D8/E8 -> 72.840407 | H8: 70 | I8: =H8+$H$8 -> 140 | J8: =I8+$H$8 -> 210 | K8: =J8+$H$8 -> 280
B9: Customer Service | C9: 6337.8495 | D9: =C9/$C$13 -> 0.11033164 | E9: 5 | F9: =1000*D9/E9 -> 22.066327 | H9: 20 | I9: =H9+$H$9 -> 40 | J9: =I9+$H$9 -> 60 | K9: =J9+$H$9 -> 80 | L9: =K9+$H$9 -> 100
B10: Working Conditions | C10: 9503.7582 | D10: =C10/$C$13 -> 0.16544495 | E10: 4 | F10: =1000*D10/E10 -> 41.361238 | H10: 40 | I10: =H10+$H$10 -> 80 | J10: =I10+$H$10 -> 120 | K10: =J10+$H$10 -> 160
B11: Work Demands | C11: 7376.0292 | D11: =C11/$C$13 -> 0.12840466 | E11: 4 | F11: =1000*D11/E11 -> 32.101164 | H11: 30 | I11: =H11+$H$11 -> 60 | J11: =I11+$H$11 -> 90 | K11: =J11+$H$11 -> 120
B13: Total | C13: =SUM(C3:C11) -> 57443.628 | D13: =SUM(D3:D11) -> 1 | I13: Total Points: | J13: =L3+M4+M5+L6+L7+K8+L9+K10+K11 -> 1005

Sheet Clusters
A1: Cluster | B1: Min Points | C1: Max Points | D1: Point Difference | E1: % spread
A2: 1 | B2: =MIN(Data!W3:W46) -> 255 | C2: =B2+D2 -> 257.55 | D2: =B2*E2 -> 2.55 | E2: 0.01
A3: 2 | B3: =C2+1 -> 258.55 | C3: =B3+D3 -> 268.892 | D3: =B3*E3 -> 10.342 | E3: =E2+3% -> 0.04
A4: 3 | B4: =C3+1 -> 269.892 | C4: =B4+D4 -> 288.78444 | D4: =B4*E4 -> 18.89244 | E4: =E3+3% -> 0.07
A5: 4 | B5: =C4+1 -> 289.78444 | C5: =B5+D5 -> 318.76288 | D5: =B5*E5 -> 28.978444 | E5: =E4+3% -> 0.1
A6: 5 | B6: =C5+1 -> 319.76288 | C6: =B6+D6 -> 361.33206 | D6: =B6*E6 -> 41.569175 | E6: =E5+3% -> 0.13
A7: 6 | B7: =C6+1 -> 362.33206 | C7: =B7+D7 -> 420.30519 | D7: =B7*E7 -> 57.973129 | E7: =E6+3% -> 0.16
A8: 7 | B8: =C7+1 -> 421.30519 | C8: =B8+D8 -> 501.35317 | D8: =B8*E8 -> 80.047986 | E8: =E7+3% -> 0.19
A9: 8 | B9: =C8+1 -> 502.35317 | C9: =B9+D9 -> 612.87087 | D9: =B9*E9 -> 110.5177 | E9: =E8+3% -> 0.22
A10: 9 | B10: =C9+1 -> 613.87087 | C10: =B10+D10 -> 767.33859 | D10: =B10*E10 -> 153.46772 | E10: =E9+3% -> 0.25
A11: 10 | B11: =C10+1 -> 768.33859 | C11: =B11+D11 -> 983.4734 | D11: =B11*E11 -> 215.13481 | E11: =E10+3% -> 0.28
A12: 11 | B12: =C11+1 -> 984.4734 | C12: =B12+D12 -> 1289.6601 | D12: =B12*E12 -> 305.18675 | E12: =E11+3% -> 0.31
A13: 12 | B13: =C12+1 -> 1290.6601 | C13: =B13+D13 -> 1729.4846 | D13: =B13*E13 -> 438.82445 | E13: =E12+3% -> 0.34
A14: 13 | B14: =C13+1 -> 1730.4846 | C14: =B14+D14 -> 2370.7639 | D14: =B14*E14 -> 640.2793 | E14: =E13+3% -> 0.37

Sheet Data
D1: SKILLS | G1: RESPONSIBILITY | L1: CONDITIONS | M1: EFFORT
A2: Position Title | B2: Department | C2: 2007 Salary | D2: Education | E2: Experience | F2: Purpose of Contacts | G2: Decision Making | H2: Accountability | I2: Contract Management | J2: Budget | K2: Customer Service | L2: Working Conditions | M2: Work Demands | N2: points_education | O2: points_experience | P2: points_purpose_contacts | Q2: points_decision | R2: points_contract | S2: points_budget | T2: points_customer | U2: points_conditions | V2: points_demands | W2: Total Points | X2: Cluster | Y2: Benchmark (in thousands of dollars) | Z2: Benchmark
A3: Administrative Clerk | B3: Quality Assurance | C3: 36260 | D3: 1 | E3: 1 | F3: 1 | G3: 1 | H3: 1 | I3: 1 | J3: 1 | K3: 1 | L3: 1 | M3: 2 | N3: =INDEX('Points Schedule'!$H$3:$M$3, MATCH(D3, 'Points Schedule'!$H$2:$M$2, 0)) -> 10 | O3: =INDEX('Points Schedule'!$H$4:$M$4, MATCH(E3, 'Points Schedule'!$H$2:$M$2, 0)) -> 15 | P3: =INDEX('Points Schedule'!$H$5:$M$5, MATCH(F3, 'Points Schedule'!$H$2:$M$2, 0)) -> 5 | Q3: =INDEX('Points Schedule'!$H$6:$M$6, MATCH(G3, 'Points Schedule'!$H$2:$M$2, 0)) -> 25 | R3: =INDEX('Points Schedule'!$H$7:$M$7, MATCH(I3, 'Points Schedule'!$H$2:$M$2, 0)) -> 10 | S3: =INDEX('Points Schedule'!$H$8:$M$8, MATCH(J3, 'Points Schedule'!$H$2:$M$2, 0)) -> 70 | T3: =INDEX('Points Schedule'!$H$9:$M$9, MATCH(K3, 'Points Schedule'!$H$2:$M$2, 0)) -> 20 | U3: =INDEX('Points Schedule'!$H$10:$M$10, MATCH(L3, 'Points Schedule'!$H$2:$M$2, 0)) -> 40 | V3: =INDEX('Points Schedule'!$H$11:$M$11, MATCH(M3, 'Points Schedule'!$H$2:$M$2, 0)) -> 60 | W3: =SUM(N3:V3) -> 255 | X3: {=INDEX(Clusters!A:A, MATCH(1, (W3>=Clusters!B:B)*(W3<=Clusters!C:C), 0))} -> 1 | Y3: 38.372611 | Z3: =Y3*1000 -> 38372.611
A4: Receptionist | B4: Ops | C4: 44526 | D4: 1 | E4: 2 | F4: 1 | G4: 1 | H4: 1 | I4: 1 | J4: 1 | K4: 2 | L4: 1 | M4: 1 | N4: =INDEX('Points Schedule'!$H$3:$M$3, MATCH(D4, 'Points Schedule'!$H$2:$M$2, 0)) -> 10 | O4: =INDEX('Points Schedule'!$H$4:$M$4, MATCH(E4, 'Points Schedule'!$H$2:$M$2, 0)) -> 30 | P4: =INDEX('Points Schedule'!$H$5:$M$5, MATCH(F4, 'Points Schedule'!$H$2:$M$2, 0)) -> 5 | Q4: =INDEX('Points Schedule'!$H$6:$M$6, MATCH(G4, 'Points Schedule'!$H$2:$M$2, 0)) -> 25 | R4: =INDEX('Points Schedule'!$H$7:$M$7, MATCH(I4, 'Points Schedule'!$H$2:$M$2, 0)) -> 10 | S4: =INDEX('Points Schedule'!$H$8:$M$8, MATCH(J4, 'Points Schedule'!$H$2:$M$2, 0)) -> 70 | T4: =INDEX('Points Schedule'!$H$9:$M$9, MATCH(K4, 'Points Schedule'!$H$2:$M$2, 0)) -> 40 | U4: =INDEX('Points Schedule'!$H$10:$M$10, MATCH(L4, 'Points Schedule'!$H$2:$M$2, 0)) -> 40 | V4: =INDEX('Points Schedule'!$H$11:$M$11, MATCH(M4, 'Points Schedule'!$H$2:$M$2, 0)) -> 30 | W4: =SUM(N4:V4) -> 260 | X4: {=INDEX(Clusters!A:A, MATCH(1, (W4>=Clusters!B:B)*(W4<=Clusters!C:C), 0))} -> 2 | Y4: 35.2879 | Z4: =Y4*1000 -> 35287.9
A5: Administrative Clerk | B5: Ops | C5: 36113 | D5: 1 | E5: 1 | F5: 1 | G5: 1 | H5: 1 | I5: 2 | J5: 1 | K5: 1 | L5: 1 | M5: 2 | N5: =INDEX('Points Schedule'!$H$3:$M$3, MATCH(D5, 'Points Schedule'!$H$2:$M$2, 0)) -> 10 | O5: =INDEX('Points Schedule'!$H$4:$M$4, MATCH(E5, 'Points Schedule'!$H$2:$M$2, 0)) -> 15 | P5: =INDEX('Points Schedule'!$H$5:$M$5, MATCH(F5, 'Points Schedule'!$H$2:$M$2, 0)) -> 5 | Q5: =INDEX('Points Schedule'!$H$6:$M$6, MATCH(G5, 'Points Schedule'!$H$2:$M$2, 0)) -> 25 | R5: =INDEX('Points Schedule'!$H$7:$M$7, MATCH(I5, 'Points Schedule'!$H$2:$M$2, 0)) -> 20 | S5: =INDEX('Points Schedule'!$H$8:$M$8, MATCH(J5, 'Points Schedule'!$H$2:$M$2, 0)) -> 70 | T5: =INDEX('Points Schedule'!$H$9:$M$9, MATCH(K5, 'Points Schedule'!$H$2:$M$2, 0)) -> 20 | U5: =INDEX('Points Schedule'!$H$10:$M$10, MATCH(L5, 'Points Schedule'!$H$2:$M$2, 0)) -> 40 | V5: =INDEX('Points Schedule'!$H$11:$M$11, MATCH(M5, 'Points Schedule'!$H$2:$M$2, 0)) -> 60 | W5: =SUM(N5:V5) -> 265 | X5: {=INDEX(Clusters!A:A, MATCH(1, (W5>=Clusters!B:B)*(W5<=Clusters!C:C), 0))} -> 2 | Y5: 38.372611 | Z5: =Y5*1000 -> 38372.611
A6: Administrative Clerk | B6: Ops | C6: 32008 | D6: 1 | E6: 1 | F6: 1 | G6: 1 | H6: 1 | I6: 2 | J6: 1 | K6: 1 | L6: 1 | M6: 2 | N6: =INDEX('Points Schedule'!$H$3:$M$3, MATCH(D6, 'Points Schedule'!$H$2:$M$2, 0)) -> 10 | O6: =INDEX('Points Schedule'!$H$4:$M$4, MATCH(E6, 'Points Schedule'!$H$2:$M$2, 0)) -> 15 | P6: =INDEX('Points Schedule'!$H$5:$M$5, MATCH(F6, 'Points Schedule'!$H$2:$M$2, 0)) -> 5 | Q6: =INDEX('Points Schedule'!$H$6:$M$6, MATCH(G6, 'Points Schedule'!$H$2:$M$2, 0)) -> 25 | R6: =INDEX('Points Schedule'!$H$7:$M$7, MATCH(I6, 'Points Schedule'!$H$2:$M$2, 0)) -> 20 | S6: =INDEX('Points Schedule'!$H$8:$M$8, MATCH(J6, 'Points Schedule'!$H$2:$M$2, 0)) -> 70 | T6: =INDEX('Points Schedule'!$H$9:$M$9, MATCH(K6, 'Points Schedule'!$H$2:$M$2, 0)) -> 20 | U6: =INDEX('Points Schedule'!$H$10:$M$10, MATCH(L6, 'Points Schedule'!$H$2:$M$2, 0)) -> 40 | V6: =INDEX('Points Schedule'!$H$11:$M$11, MATCH(M6, 'Points Schedule'!$H$2:$M$2, 0)) -> 60 | W6: =SUM(N6:V6) -> 265 | X6: {=INDEX(Clusters!A:A, MATCH(1, (W6>=Clusters!B:B)*(W6<=Clusters!C:C), 0))} -> 2 | Y6: 38.372611 | Z6: =Y6*1000 -> 38372.611
A7: Meetings and District Programs Coordinator | B7: Continuing Education | C7: 42908 | D7: 3 | E7: 1 | F7: 2 | G7: 1 | H7: 1 | I7: 2 | J7: 1 | K7: 2 | L7: 1 | M7: 1 | N7: =INDEX('Points Schedule'!$H$3:$M$3, MATCH(D7, 'Points Schedule'!$H$2:$M$2, 0)) -> 30 | O7: =INDEX('Points Schedule'!$H$4:$M$4, MATCH(E7, 'Points Schedule'!$H$2:$M$2, 0)) -> 15 | P7: =INDEX('Points Schedule'!$H$5:$M$5, MATCH(F7, 'Points Schedule'!$H$2:$M$2, 0)) -> 10 | Q7: =INDEX('Points Schedule'!$H$6:$M$6, MATCH(G7, 'Points Schedule'!$H$2:$M$2, 0)) -> 25 | R7: =INDEX('Points Schedule'!$H$7:$M$7, MATCH(I7, 'Points Schedule'!$H$2:$M$2, 0)) -> 20 | S7: =INDEX('Points Schedule'!$H$8:$M$8, MATCH(J7, 'Points Schedule'!$H$2:$M$2, 0)) -> 70 | T7: =INDEX('Points Schedule'!$H$9:$M$9, MATCH(K7, 'Points Schedule'!$H$2:$M$2, 0)) -> 40 | U7: =INDEX('Points Schedule'!$H$10:$M$10, MATCH(L7, 'Points Schedule'!$H$2:$M$2, 0)) -> 40 | V7: =INDEX('Points Schedule'!$H$11:$M$11, MATCH(M7, 'Points Schedule'!$H$2:$M$2, 0)) -> 30 | W7: =SUM(N7:V7) -> 280 | X7: 3 | Y7: 50.257143 | Z7: =Y7*1000 -> 50257.143
A8: Circulation Technician & Receptionist | B8: Ops | C8: 46481 | D8: 3 | E8: 2 | F8: 1 | G8: 1 | H8: 1 | I8: 1 | J8: 1 | K8: 2 | L8: 1 | M8: 1 | N8: =INDEX('Points Schedule'!$H$3:$M$3, MATCH(D8, 'Points Schedule'!$H$2:$M$2, 0)) -> 30 | O8: =INDEX('Points Schedule'!$H$4:$M$4, MATCH(E8, 'Points Schedule'!$H$2:$M$2, 0)) -> 30 | P8: =INDEX('Points Schedule'!$H$5:$M$5, MATCH(F8, 'Points Schedule'!$H$2:$M$2, 0)) -> 5 | Q8: =INDEX('Points Schedule'!$H$6:$M$6, MATCH(G8, 'Points Schedule'!$H$2:$M$2, 0)) -> 25 | R8: =INDEX('Points Schedule'!$H$7:$M$7, MATCH(I8, 'Points Schedule'!$H$2:$M$2, 0)) -> 10 | S8: =INDEX('Points Schedule'!$H$8:$M$8, MATCH(J8, 'Points Schedule'!$H$2:$M$2, 0)) -> 70 | T8: =INDEX('Points Schedule'!$H$9:$M$9, MATCH(K8, 'Points Schedule'!$H$2:$M$2, 0)) -> 40 | U8: =INDEX('Points Schedule'!$H$10:$M$10, MATCH(L8, 'Points Schedule'!$H$2:$M$2, 0)) -> 40 | V8: =INDEX('Points Schedule'!$H$11:$M$11, MATCH(M8, 'Points Schedule'!$H$2:$M$2, 0)) -> 30 | W8: =SUM(N8:V8) -> 280 | X8: {=INDEX(Clusters!A:A, MATCH(1, (W8>=Clusters!B:B)*(W8<=Clusters!C:C), 0))} -> 3
A9: Seminar Coordinator | B9: Continuing Education | C9: 38513 | D9: 3 | E9: 1 | F9: 2 | G9: 1 | H9: 1 | I9: 2 | J9: 1 | K9: 2 | L9: 1 | M9: 1 | N9: =INDEX('Points Schedule'!$H$3:$M$3, MATCH(D9, 'Points Schedule'!$H$2:$M$2, 0)) -> 30 | O9: =INDEX('Points Schedule'!$H$4:$M$4, MATCH(E9, 'Points Schedule'!$H$2:$M$2, 0)) -> 15 | P9: =INDEX('Points Schedule'!$H$5:$M$5, MATCH(F9, 'Points Schedule'!$H$2:$M$2, 0)) -> 10 | Q9: =INDEX('Points Schedule'!$H$6:$M$6, MATCH(G9, 'Points Schedule'!$H$2:$M$2, 0)) -> 25 | R9: =INDEX('Points Schedule'!$H$7:$M$7, MATCH(I9, 'Points Schedule'!$H$2:$M$2, 0)) -> 20 | S9: =INDEX('Points Schedule'!$H$8:$M$8, MATCH(J9, 'Points Schedule'!$H$2:$M$2, 0)) -> 70 | T9: =INDEX('Points Schedule'!$H$9:$M$9, MATCH(K9, 'Points Schedule'!$H$2:$M$2, 0)) -> 40 | U9: =INDEX('Points Schedule'!$H$10:$M$10, MATCH(L9, 'Points Schedule'!$H$2:$M$2, 0)) -> 40 | V9: =INDEX('Points Schedule'!$H$11:$M$11, MATCH(M9, 'Points Schedule'!$H$2:$M$2, 0)) -> 30 | W9: =SUM(N9:V9) -> 280 | X9: {=INDEX(Clusters!A:A, MATCH(1, (W9>=Clusters!B:B)*(W9<=Clusters!C:C), 0))} -> 3 | Y9: 50.257143 | Z9: =Y9*1000 -> 50257.143
A10: Seminar Coordinator | B10: Continuing Education | C10: 37370 | D10: 3 | E10: 1 | F10: 2 | G10: 1 | H10: 1 | I10: 2 | J10: 1 | K10: 2 | L10: 1 | M10: 1 | N10: =INDEX('Points Schedule'!$H$3:$M$3, MATCH(D10, 'Points Schedule'!$H$2:$M$2, 0)) -> 30 | O10: =INDEX('Points Schedule'!$H$4:$M$4, MATCH(E10, 'Points Schedule'!$H$2:$M$2, 0)) -> 15 | P10: =INDEX('Points Schedule'!$H$5:$M$5, MATCH(F10, 'Points Schedule'!$H$2:$M$2, 0)) -> 10 | Q10: =INDEX('Points Schedule'!$H$6:$M$6, MATCH(G10, 'Points Schedule'!$H$2:$M$2, 0)) -> 25 | R10: =INDEX('Points Schedule'!$H$7:$M$7, MATCH(I10, 'Points Schedule'!$H$2:$M$2, 0)) -> 20 | S10: =INDEX('Points Schedule'!$H$8:$M$8, MATCH(J10, 'Points Schedule'!$H$2:$M$2, 0)) -> 70 | T10: =INDEX('Points Schedule'!$H$9:$M$9, MATCH(K10, 'Points Schedule'!$H$2:$M$2, 0)) -> 40 | U10: =INDEX('Points Schedule'!$H$10:$M$10, MATCH(L10, 'Points Schedule'!$H$2:$M$2, 0)) -> 40 | V10: =INDEX('Points Schedule'!$H$11:$M$11, MATCH(M10, 'Points Schedule'!$H$2:$M$2, 0)) -> 30 | W10: =SUM(N10:V10) -> 280 | X10: {=INDEX(Clusters!A:A, MATCH(1, (W10>=Clusters!B:B)*(W10<=Clusters!C:C), 0))} -> 3 | Y10: 50.257143 | Z10: =Y10*1000 -> 50257.143
A11: Secretary (Director Continuing Education) | B11: Continuing Education | C11: 43898 | D11: 2 | E11: 1 | F11: 1 | G11: 1 | H11: 1 | I11: 2 | J11: 1 | K11: 3 | L11: 1 | M11: 1 | N11: =INDEX('Points Schedule'!$H$3:$M$3, MATCH(D11, 'Points Schedule'!$H$2:$M$2, 0)) -> 20 | O11: =INDEX('Points Schedule'!$H$4:$M$4, MATCH(E11, 'Points Schedule'!$H$2:$M$2, 0)) -> 15 | P11: =INDEX('Points Schedule'!$H$5:$M$5, MATCH(F11, 'Points Schedule'!$H$2:$M$2, 0)) -> 5 | Q11: =INDEX('Points Schedule'!$H$6:$M$6, MATCH(G11, 'Points Schedule'!$H$2:$M$2, 0)) -> 25 | R11: =INDEX('Points Schedule'!$H$7:$M$7, MATCH(I11, 'Points Schedule'!$H$2:$M$2, 0)) -> 20 | S11: =INDEX('Points Schedule'!$H$8:$M$8, MATCH(J11, 'Points Schedule'!$H$2:$M$2, 0)) -> 70 | T11: =INDEX('Points Schedule'!$H$9:$M$9, MATCH(K11, 'Points Schedule'!$H$2:$M$2, 0)) -> 60 | U11: =INDEX('Points Schedule'!$H$10:$M$10, MATCH(L11, 'Points Schedule'!$H$2:$M$2, 0)) -> 40 | V11: =INDEX('Points Schedule'!$H$11:$M$11, MATCH(M11, 'Points Schedule'!$H$2:$M$2, 0)) -> 30 | W11: =SUM(N11:V11) -> 285 | X11: {=INDEX(Clusters!A:A, MATCH(1, (W11>=Clusters!B:B)*(W11<=Clusters!C:C), 0))} -> 3 | Y11: 47.838276 | Z11: =Y11*1000 -> 47838.276
A12: Junior Systems Administrator | B12: IT | C12: 41500 | D12: 3 | E12: 1 | F12: 1 | G12: 2 | H12: 1 | I12: 1 | J12: 1 | K12: 2 | L12: 1 | M12: 1 | N12: =INDEX('Points Schedule'!$H$3:$M$3, MATCH(D12, 'Points Schedule'!$H$2:$M$2, 0)) -> 30 | O12: =INDEX('Points Schedule'!$H$4:$M$4, MATCH(E12, 'Points Schedule'!$H$2:$M$2, 0)) -> 15 | P12: =INDEX('Points Schedule'!$H$5:$M$5, MATCH(F12, 'Points Schedule'!$H$2:$M$2, 0)) -> 5 | Q12: =INDEX('Points Schedule'!$H$6:$M$6, MATCH(G12, 'Points Schedule'!$H$2:$M$2, 0)) -> 50 | R12: =INDEX('Points Schedule'!$H$7:$M$7, MATCH(I12, 'Points Schedule'!$H$2:$M$2, 0)) -> 10 | S12: =INDEX('Points Schedule'!$H$8:$M$8, MATCH(J12, 'Points Schedule'!$H$2:$M$2, 0)) -> 70 | T12: =INDEX('Points Schedule'!$H$9:$M$9, MATCH(K12, 'Points Schedule'!$H$2:$M$2, 0)) -> 40 | U12: =INDEX('Points Schedule'!$H$10:$M$10, MATCH(L12, 'Points Schedule'!$H$2:$M$2, 0)) -> 40 | V12: =INDEX('Points Schedule'!$H$11:$M$11, MATCH(M12, 'Points Schedule'!$H$2:$M$2, 0)) -> 30 | W12: =SUM(N12:V12) -> 290 | X12: {=INDEX(Clusters!A:A, MATCH(1, (W12>=Clusters!B:B)*(W12<=Clusters!C:C), 0))} -> 4
A13: Administrative Assistant, Exec Office | B13: Exec | C13: 37258 | D13: 1 | E13: 1 | F13: 2 | G13: 1 | H13: 1 | I13: 1 | J13: 1 | K13: 2 | L13: 2 | M13: 1 | N13: =INDEX('Points Schedule'!$H$3:$M$3, MATCH(D13, 'Points Schedule'!$H$2:$M$2, 0)) -> 10 | O13: =INDEX('Points Schedule'!$H$4:$M$4, MATCH(E13, 'Points Schedule'!$H$2:$M$2, 0)) -> 15 | P13: =INDEX('Points Schedule'!$H$5:$M$5, MATCH(F13, 'Points Schedule'!$H$2:$M$2, 0)) -> 10 | Q13: =INDEX('Points Schedule'!$H$6:$M$6, MATCH(G13, 'Points Schedule'!$H$2:$M$2, 0)) -> 25 | R13: =INDEX('Points Schedule'!$H$7:$M$7, MATCH(I13, 'Points Schedule'!$H$2:$M$2, 0)) -> 10 | S13: =INDEX('Points Schedule'!$H$8:$M$8, MATCH(J13, 'Points Schedule'!$H$2:$M$2, 0)) -> 70 | T13: =INDEX('Points Schedule'!$H$9:$M$9, MATCH(K13, 'Points Schedule'!$H$2:$M$2, 0)) -> 40 | U13: =INDEX('Points Schedule'!$H$10:$M$10, MATCH(L13, 'Points Schedule'!$H$2:$M$2, 0)) -> 80 | V13: =INDEX('Points Schedule'!$H$11:$M$11, MATCH(M13, 'Points Schedule'!$H$2:$M$2, 0)) -> 30 | W13: =SUM(N13:V13) -> 290 | X13: {=INDEX(Clusters!A:A, MATCH(1, (W13>=Clusters!B:B)*(W13<=Clusters!C:C), 0))} -> 4 | Y13: 55.49247 | Z13: =Y13*1000 -> 55492.47
A14: Junior Accountant | B14: Ops | C14: 32810 | D14: 2 | E14: 1 | F14: 1 | G14: 1 | H14: 1 | I14: 2 | J14: 1 | K14: 2 | L14: 1 | M14: 2 | N14: =INDEX('Points Schedule'!$H$3:$M$3, MATCH(D14, 'Points Schedule'!$H$2:$M$2, 0)) -> 20 | O14: =INDEX('Points Schedule'!$H$4:$M$4, MATCH(E14, 'Points Schedule'!$H$2:$M$2, 0)) -> 15 | P14: =INDEX('Points Schedule'!$H$5:$M$5, MATCH(F14, 'Points Schedule'!$H$2:$M$2, 0)) -> 5 | Q14: =INDEX('Points Schedule'!$H$6:$M$6, MATCH(G14, 'Points Schedule'!$H$2:$M$2, 0)) -> 25 | R14: =INDEX('Points Schedule'!$H$7:$M$7, MATCH(I14, 'Points Schedule'!$H$2:$M$2, 0)) -> 20 | S14: =INDEX('Points Schedule'!$H$8:$M$8, MATCH(J14, 'Points Schedule'!$H$2:$M$2, 0)) -> 70 | T14: =INDEX('Points Schedule'!$H$9:$M$9, MATCH(K14, 'Points Schedule'!$H$2:$M$2, 0)) -> 40 | U14: =INDEX('Points Schedule'!$H$10:$M$10, MATCH(L14, 'Points Schedule'!$H$2:$M$2, 0)) -> 40 | V14: =INDEX('Points Schedule'!$H$11:$M$11, MATCH(M14, 'Points Schedule'!$H$2:$M$2, 0)) -> 60 | W14: =SUM(N14:V14) -> 295 | X14: {=INDEX(Clusters!A:A, MATCH(1, (W14>=Clusters!B:B)*(W14<=Clusters!C:C), 0))} -> 4 | Y14: 44.119737 | Z14: =Y14*1000 -> 44119.737
A15: Business Research Coordinator | B15: Ops | C15: 58000 | D15: 3 | E15: 2 | F15: 2 | G15: 1 | H15: 1 | I15: 2 | J15: 1 | K15: 2 | L15: 1 | M15: 1 | N15: =INDEX('Points Schedule'!$H$3:$M$3, MATCH(D15, 'Points Schedule'!$H$2:$M$2, 0)) -> 30 | O15: =INDEX('Points Schedule'!$H$4:$M$4, MATCH(E15, 'Points Schedule'!$H$2:$M$2, 0)) -> 30 | P15: =INDEX('Points Schedule'!$H$5:$M$5, MATCH(F15, 'Points Schedule'!$H$2:$M$2, 0)) -> 10 | Q15: =INDEX('Points Schedule'!$H$6:$M$6, MATCH(G15, 'Points Schedule'!$H$2:$M$2, 0)) -> 25 | R15: =INDEX('Points Schedule'!$H$7:$M$7, MATCH(I15, 'Points Schedule'!$H$2:$M$2, 0)) -> 20 | S15: =INDEX('Points Schedule'!$H$8:$M$8, MATCH(J15, 'Points Schedule'!$H$2:$M$2, 0)) -> 70 | T15: =INDEX('Points Schedule'!$H$9:$M$9, MATCH(K15, 'Points Schedule'!$H$2:$M$2, 0)) -> 40 | U15: =INDEX('Points Schedule'!$H$10:$M$10, MATCH(L15, 'Points Schedule'!$H$2:$M$2, 0)) -> 40 | V15: =INDEX('Points Schedule'!$H$11:$M$11, MATCH(M15, 'Points Schedule'!$H$2:$M$2, 0)) -> 30 | W15: =SUM(N15:V15) -> 295 | X15: {=INDEX(Clusters!A:A, MATCH(1, (W15>=Clusters!B:B)*(W15<=Clusters!C:C), 0))} -> 4
A16: Administrative Clerk/mailroom clerk | B16: Ops | C16: 40429 | D16: 1 | E16: 1 | F16: 2 | G16: 1 | H16: 1 | I16: 1 | J16: 1 | K16: 1 | L16: 3 | M16: 1 | N16: =INDEX('Points Schedule'!$H$3:$M$3, MATCH(D16, 'Points Schedule'!$H$2:$M$2, 0)) -> 10 | O16: =INDEX('Points Schedule'!$H$4:$M$4, MATCH(E16, 'Points Schedule'!$H$2:$M$2, 0)) -> 15 | P16: =INDEX('Points Schedule'!$H$5:$M$5, MATCH(F16, 'Points Schedule'!$H$2:$M$2, 0)) -> 10 | Q16: =INDEX('Points Schedule'!$H$6:$M$6, MATCH(G16, 'Points Schedule'!$H$2:$M$2, 0)) -> 25 | R16: =INDEX('Points Schedule'!$H$7:$M$7, MATCH(I16, 'Points Schedule'!$H$2:$M$2, 0)) -> 10 | S16: =INDEX('Points Schedule'!$H$8:$M$8, MATCH(J16, 'Points Schedule'!$H$2:$M$2, 0)) -> 70 | T16: =INDEX('Points Schedule'!$H$9:$M$9, MATCH(K16, 'Points Schedule'!$H$2:$M$2, 0)) -> 20 | U16: =INDEX('Points Schedule'!$H$10:$M$10, MATCH(L16, 'Points Schedule'!$H$2:$M$2, 0)) -> 120 | V16: =INDEX('Points Schedule'!$H$11:$M$11, MATCH(M16, 'Points Schedule'!$H$2:$M$2, 0)) -> 30 | W16: =SUM(N16:V16) -> 310 | X16: {=INDEX(Clusters!A:A, MATCH(1, (W16>=Clusters!B:B)*(W16<=Clusters!C:C), 0))} -> 4 | Y16: 39.200926 | Z16: =Y16*1000 -> 39200.926
A17: Accountant | B17: Ops | C17: 41530 | D17: 3 | E17: 2 | F17: 2 | G17: 2 | H17: 1 | I17: 2 | J17: 1 | K17: 1 | L17: 1 | M17: 2 | N17: =INDEX('Points Schedule'!$H$3:$M$3, MATCH(D17, 'Points Schedule'!$H$2:$M$2, 0)) -> 30 | O17: =INDEX('Points Schedule'!$H$4:$M$4, MATCH(E17, 'Points Schedule'!$H$2:$M$2, 0)) -> 30 | P17: =INDEX('Points Schedule'!$H$5:$M$5, MATCH(F17, 'Points Schedule'!$H$2:$M$2, 0)) -> 10 | Q17: =INDEX('Points Schedule'!$H$6:$M$6, MATCH(G17, 'Points Schedule'!$H$2:$M$2, 0)) -> 50 | R17: =INDEX('Points Schedule'!$H$7:$M$7, MATCH(I17, 'Points Schedule'!$H$2:$M$2, 0)) -> 20 | S17: =INDEX('Points Schedule'!$H$8:$M$8, MATCH(J17, 'Points Schedule'!$H$2:$M$2, 0)) -> 70 | T17: =INDEX('Points Schedule'!$H$9:$M$9, MATCH(K17, 'Points Schedule'!$H$2:$M$2, 0)) -> 20 | U17: =INDEX('Points Schedule'!$H$10:$M$10, MATCH(L17, 'Points Schedule'!$H$2:$M$2, 0)) -> 40 | V17: =INDEX('Points Schedule'!$H$11:$M$11, MATCH(M17, 'Points Schedule'!$H$2:$M$2, 0)) -> 60 | W17: =SUM(N17:V17) -> 330 | X17: {=INDEX(Clusters!A:A, MATCH(1, (W17>=Clusters!B:B)*(W17<=Clusters!C:C), 0))} -> 5 | Y17: 53.229843 | Z17: =Y17*1000 -> 53229.843
A18: Programmer | B18: IT | C18: 77289 | D18: 3 | E18: 2 | F18: 1 | G18: 2 | H18: 1 | I18: 1 | J18: 1 | K18: 2 | L18: 1 | M18: 2 | N18: =INDEX('Points Schedule'!$H$3:$M$3, MATCH(D18, 'Points Schedule'!$H$2:$M$2, 0)) -> 30 | O18: =INDEX('Points Schedule'!$H$4:$M$4, MATCH(E18, 'Points Schedule'!$H$2:$M$2, 0)) -> 30 | P18: =INDEX('Points Schedule'!$H$5:$M$5, MATCH(F18, 'Points Schedule'!$H$2:$M$2, 0)) -> 5 | Q18: =INDEX('Points Schedule'!$H$6:$M$6, MATCH(G18, 'Points Schedule'!$H$2:$M$2, 0)) -> 50 | R18: =INDEX('Points Schedule'!$H$7:$M$7, MATCH(I18, 'Points Schedule'!$H$2:$M$2, 0)) -> 10 | S18: =INDEX('Points Schedule'!$H$8:$M$8, MATCH(J18, 'Points Schedule'!$H$2:$M$2, 0)) -> 70 | T18: =INDEX('Points Schedule'!$H$9:$M$9, MATCH(K18, 'Points Schedule'!$H$2:$M$2, 0)) -> 40 | U18: =INDEX('Points Schedule'!$H$10:$M$10, MATCH(L18, 'Points Schedule'!$H$2:$M$2, 0)) -> 40 | V18: =INDEX('Points Schedule'!$H$11:$M$11, MATCH(M18, 'Points Schedule'!$H$2:$M$2, 0)) -> 60 | W18: =SUM(N18:V18) -> 335 | X18: {=INDEX(Clusters!A:A, MATCH(1, (W18>=Clusters!B:B)*(W18<=Clusters!C:C), 0))} -> 5
A19: Career Consultant | B19: Ops | C19: 68700 | D19: 3 | E19: 3 | F19: 2 | G19: 1 | H19: 1 | I19: 1 | J19: 1 | K19: 4 | L19: 1 | M19: 1 | N19: =INDEX('Points Schedule'!$H$3:$M$3, MATCH(D19, 'Points Schedule'!$H$2:$M$2, 0)) -> 30 | O19: =INDEX('Points Schedule'!$H$4:$M$4, MATCH(E19, 'Points Schedule'!$H$2:$M$2, 0)) -> 45 | P19: =INDEX('Points Schedule'!$H$5:$M$5, MATCH(F19, 'Points Schedule'!$H$2:$M$2, 0)) -> 10 | Q19: =INDEX('Points Schedule'!$H$6:$M$6, MATCH(G19, 'Points Schedule'!$H$2:$M$2, 0)) -> 25 | R19: =INDEX('Points Schedule'!$H$7:$M$7, MATCH(I19, 'Points Schedule'!$H$2:$M$2, 0)) -> 10 | S19: =INDEX('Points Schedule'!$H$8:$M$8, MATCH(J19, 'Points Schedule'!$H$2:$M$2, 0)) -> 70 | T19: =INDEX('Points Schedule'!$H$9:$M$9, MATCH(K19, 'Points Schedule'!$H$2:$M$2, 0)) -> 80 | U19: =INDEX('Points Schedule'!$H$10:$M$10, MATCH(L19, 'Points Schedule'!$H$2:$M$2, 0)) -> 40 | V19: =INDEX('Points Schedule'!$H$11:$M$11, MATCH(M19, 'Points Schedule'!$H$2:$M$2, 0)) -> 30 | W19: =SUM(N19:V19) -> 340 | X19: {=INDEX(Clusters!A:A, MATCH(1, (W19>=Clusters!B:B)*(W19<=Clusters!C:C), 0))} -> 5
A20: Associate Coordinator, Professional Programs | B20: Continuing Education | C20: 39104 | D20: 3 | E20: 3 | F20: 1 | G20: 1 | H20: 1 | I20: 1 | J20: 1 | K20: 3 | L20: 1 | M20: 2 | N20: =INDEX('Points Schedule'!$H$3:$M$3, MATCH(D20, 'Points Schedule'!$H$2:$M$2, 0)) -> 30 | O20: =INDEX('Points Schedule'!$H$4:$M$4, MATCH(E20, 'Points Schedule'!$H$2:$M$2, 0)) -> 45 | P20: =INDEX('Points Schedule'!$H$5:$M$5, MATCH(F20, 'Points Schedule'!$H$2:$M$2, 0)) -> 5 | Q20: =INDEX('Points Schedule'!$H$6:$M$6, MATCH(G20, 'Points Schedule'!$H$2:$M$2, 0)) -> 25 | R20: =INDEX('Points Schedule'!$H$7:$M$7, MATCH(I20, 'Points Schedule'!$H$2:$M$2, 0)) -> 10 | S20: =INDEX('Points Schedule'!$H$8:$M$8, MATCH(J20, 'Points Schedule'!$H$2:$M$2, 0)) -> 70 | T20: =INDEX('Points Schedule'!$H$9:$M$9, MATCH(K20, 'Points Schedule'!$H$2:$M$2, 0)) -> 60 | U20: =INDEX('Points Schedule'!$H$10:$M$10, MATCH(L20, 'Points Schedule'!$H$2:$M$2, 0)) -> 40 | V20: =INDEX('Points Schedule'!$H$11:$M$11, MATCH(M20, 'Points Schedule'!$H$2:$M$2, 0)) -> 60 | W20: =SUM(N20:V20) -> 345 | X20: {=INDEX(Clusters!A:A, MATCH(1, (W20>=Clusters!B:B)*(W20<=Clusters!C:C), 0))} -> 5
A21: Secretary (Director Operations) | B21: Ops | C21: 49508 | D21: 2 | E21: 3 | F21: 2 | G21: 1 | H21: 1 | I21: 1 | J21: 1 | K21: 2 | L21: 1 | M21: 3 | N21: =INDEX('Points Schedule'!$H$3:$M$3, MATCH(D21, 'Points Schedule'!$H$2:$M$2, 0)) -> 20 | O21: =INDEX('Points Schedule'!$H$4:$M$4, MATCH(E21, 'Points Schedule'!$H$2:$M$2, 0)) -> 45 | P21: =INDEX('Points Schedule'!$H$5:$M$5, MATCH(F21, 'Points Schedule'!$H$2:$M$2, 0)) -> 10 | Q21: =INDEX('Points Schedule'!$H$6:$M$6, MATCH(G21, 'Points Schedule'!$H$2:$M$2, 0)) -> 25 | R21: =INDEX('Points Schedule'!$H$7:$M$7, MATCH(I21, 'Points Schedule'!$H$2:$M$2, 0)) -> 10 | S21: =INDEX('Points Schedule'!$H$8:$M$8, MATCH(J21, 'Points Schedule'!$H$2:$M$2, 0)) -> 70 | T21: =INDEX('Points Schedule'!$H$9:$M$9, MATCH(K21, 'Points Schedule'!$H$2:$M$2, 0)) -> 40 | U21: =INDEX('Points Schedule'!$H$10:$M$10, MATCH(L21, 'Points Schedule'!$H$2:$M$2, 0)) -> 40 | V21: =INDEX('Points Schedule'!$H$11:$M$11, MATCH(M21, 'Points Schedule'!$H$2:$M$2, 0)) -> 90 | W21: =SUM(N21:V21) -> 350 | X21: {=INDEX(Clusters!A:A, MATCH(1, (W21>=Clusters!B:B)*(W21<=Clusters!C:C), 0))} -> 5 | Y21: 47.838276 | Z21: =Y21*1000 -> 47838.276
A22: Business Analyst | B22: Ops | C22: 63348 | D22: 3 | E22: 2 | F22: 2 | G22: 2 | H22: 1 | I22: 1 | J22: 1 | K22: 1 | L22: 1 | M22: 3 | N22: =INDEX('Points Schedule'!$H$3:$M$3, MATCH(D22, 'Points Schedule'!$H$2:$M$2, 0)) -> 30 | O22: =INDEX('Points Schedule'!$H$4:$M$4, MATCH(E22, 'Points Schedule'!$H$2:$M$2, 0)) -> 30 | P22: =INDEX('Points Schedule'!$H$5:$M$5, MATCH(F22, 'Points Schedule'!$H$2:$M$2, 0)) -> 10 | Q22: =INDEX('Points Schedule'!$H$6:$M$6, MATCH(G22, 'Points Schedule'!$H$2:$M$2, 0)) -> 50 | R22: =INDEX('Points Schedule'!$H$7:$M$7, MATCH(I22, 'Points Schedule'!$H$2:$M$2, 0)) -> 10 | S22: =INDEX('Points Schedule'!$H$8:$M$8, MATCH(J22, 'Points Schedule'!$H$2:$M$2, 0)) -> 70 | T22: =INDEX('Points Schedule'!$H$9:$M$9, MATCH(K22, 'Points Schedule'!$H$2:$M$2, 0)) -> 20 | U22: =INDEX('Points Schedule'!$H$10:$M$10, MATCH(L22, 'Points Schedule'!$H$2:$M$2, 0)) -> 40 | V22: =INDEX('Points Schedule'!$H$11:$M$11, MATCH(M22, 'Points Schedule'!$H$2:$M$2, 0)) -> 90 | W22: =SUM(N22:V22) -> 350 | X22: {=INDEX(Clusters!A:A, MATCH(1, (W22>=Clusters!B:B)*(W22<=Clusters!C:C), 0))} -> 5
A23: Peer Review Administrator, Audit | B23: Quality Assurance | C23: 56000 | D23: 3 | E23: 2 | F23: 2 | G23: 1 | H23: 1 | I23: 1 | J23: 1 | K23: 2 | L23: 2 | M23: 2 | N23: =INDEX('Points Schedule'!$H$3:$M$3, MATCH(D23, 'Points Schedule'!$H$2:$M$2, 0)) -> 30 | O23: =INDEX('Points Schedule'!$H$4:$M$4, MATCH(E23, 'Points Schedule'!$H$2:$M$2, 0)) -> 30 | P23: =INDEX('Points Schedule'!$H$5:$M$5, MATCH(F23, 'Points Schedule'!$H$2:$M$2, 0)) -> 10 | Q23: =INDEX('Points Schedule'!$H$6:$M$6, MATCH(G23, 'Points Schedule'!$H$2:$M$2, 0)) -> 25 | R23: =INDEX('Points Schedule'!$H$7:$M$7, MATCH(I23, 'Points Schedule'!$H$2:$M$2, 0)) -> 10 | S23: =INDEX('Points Schedule'!$H$8:$M$8, MATCH(J23, 'Points Schedule'!$H$2:$M$2, 0)) -> 70 | T23: =INDEX('Points Schedule'!$H$9:$M$9, MATCH(K23, 'Points Schedule'!$H$2:$M$2, 0)) -> 40 | U23: =INDEX('Points Schedule'!$H$10:$M$10, MATCH(L23, 'Points Schedule'!$H$2:$M$2, 0)) -> 80 | V23: =INDEX('Points Schedule'!$H$11:$M$11, MATCH(M23, 'Points Schedule'!$H$2:$M$2, 0)) -> 60 | W23: =SUM(N23:V23) -> 355 | X23: {=INDEX(Clusters!A:A, MATCH(1, (W23>=Clusters!B:B)*(W23<=Clusters!C:C), 0))} -> 5
A24: Peer Review Administrator, Audit | B24: Quality Assurance | C24: 54390 | D24: 3 | E24: 2 | F24: 2 | G24: 1 | H24: 1 | I24: 1 | J24: 1 | K24: 2 | L24: 2 | M24: 2 | N24: =INDEX('Points Schedule'!$H$3:$M$3, MATCH(D24, 'Points Schedule'!$H$2:$M$2, 0)) -> 30 | O24: =INDEX('Points Schedule'!$H$4:$M$4, MATCH(E24, 'Points Schedule'!$H$2:$M$2, 0)) -> 30 | P24: =INDEX('Points Schedule'!$H$5:$M$5, MATCH(F24, 'Points Schedule'!$H$2:$M$2, 0)) -> 10 | Q24: =INDEX('Points Schedule'!$H$6:$M$6, MATCH(G24, 'Points Schedule'!$H$2:$M$2, 0)) -> 25 | R24: =INDEX('Points Schedule'!$H$7:$M$7, MATCH(I24, 'Points Schedule'!$H$2:$M$2, 0)) -> 10 | S24: =INDEX('Points Schedule'!$H$8:$M$8, MATCH(J24, 'Points Schedule'!$H$2:$M$2, 0)) -> 70 | T24: =INDEX('Points Schedule'!$H$9:$M$9, MATCH(K24, 'Points Schedule'!$H$2:$M$2, 0)) -> 40 | U24: =INDEX('Points Schedule'!$H$10:$M$10, MATCH(L24, 'Points Schedule'!$H$2:$M$2, 0)) -> 80 | V24: =INDEX('Points Schedule'!$H$11:$M$11, MATCH(M24, 'Points Schedule'!$H$2:$M$2, 0)) -> 60 | W24: =SUM(N24:V24) -> 355 | X24: {=INDEX(Clusters!A:A, MATCH(1, (W24>=Clusters!B:B)*(W24<=Clusters!C:C), 0))} -> 5
A25: Peer Review Administrator, Tax | B25: Quality Assurance | C25: 58700 | D25: 3 | E25: 2 | F25: 2 | G25: 2 | H25: 1 | I25: 1 | J25: 1 | K25: 1 | L25: 2 | M25: 2 | N25: =INDEX('Points Schedule'!$H$3:$M$3, MATCH(D25, 'Points Schedule'!$H$2:$M$2, 0)) -> 30 | O25: =INDEX('Points Schedule'!$H$4:$M$4, MATCH(E25, 'Points Schedule'!$H$2:$M$2, 0)) -> 30 | P25: =INDEX('Points Schedule'!$H$5:$M$5, MATCH(F25, 'Points Schedule'!$H$2:$M$2, 0)) -> 10 | Q25: =INDEX('Points Schedule'!$H$6:$M$6, MATCH(G25, 'Points Schedule'!$H$2:$M$2, 0)) -> 50 | R25: =INDEX('Points Schedule'!$H$7:$M$7, MATCH(I25, 'Points Schedule'!$H$2:$M$2, 0)) -> 10 | S25: =INDEX('Points Schedule'!$H$8:$M$8, MATCH(J25, 'Points Schedule'!$H$2:$M$2, 0)) -> 70 | T25: =INDEX('Points Schedule'!$H$9:$M$9, MATCH(K25, 'Points Schedule'!$H$2:$M$2, 0)) -> 20 | U25: =INDEX('Points Schedule'!$H$10:$M$10, MATCH(L25, 'Points Schedule'!$H$2:$M$2, 0)) -> 80 | V25: =INDEX('Points Schedule'!$H$11:$M$11, MATCH(M25, 'Points Schedule'!$H$2:$M$2, 0)) -> 60 | W25: =SUM(N25:V25) -> 360 | X25: {=INDEX(Clusters!A:A, MATCH(1, (W25>=Clusters!B:B)*(W25<=Clusters!C:C), 0))} -> 5
A26: Information Officer | B26: Marketing | C26: 55233 | D26: 3 | E26: 1 | F26: 2 | G26: 2 | H26: 1 | I26: 2 | J26: 1 | K26: 1 | L26: 3 | M26: 1 | N26: =INDEX('Points Schedule'!$H$3:$M$3, MATCH(D26, 'Points Schedule'!$H$2:$M$2, 0)) -> 30 | O26: =INDEX('Points Schedule'!$H$4:$M$4, MATCH(E26, 'Points Schedule'!$H$2:$M$2, 0)) -> 15 | P26: =INDEX('Points Schedule'!$H$5:$M$5, MATCH(F26, 'Points Schedule'!$H$2:$M$2, 0)) -> 10 | Q26: =INDEX('Points Schedule'!$H$6:$M$6, MATCH(G26, 'Points Schedule'!$H$2:$M$2, 0)) -> 50 | R26: =INDEX('Points Schedule'!$H$7:$M$7, MATCH(I26, 'Points Schedule'!$H$2:$M$2, 0)) -> 20 | S26: =INDEX('Points Schedule'!$H$8:$M$8, MATCH(J26, 'Points Schedule'!$H$2:$M$2, 0)) -> 70 | T26: =INDEX('Points Schedule'!$H$9:$M$9, MATCH(K26, 'Points Schedule'!$H$2:$M$2, 0)) -> 20 | U26: =INDEX('Points Schedule'!$H$10:$M$10, MATCH(L26, 'Points Schedule'!$H$2:$M$2, 0)) -> 120 | V26: =INDEX('Points Schedule'!$H$11:$M$11, MATCH(M26, 'Points Schedule'!$H$2:$M$2, 0)) -> 30 | W26: =SUM(N26:V26) -> 365 | X26: {=INDEX(Clusters!A:A, MATCH(1, (W26>=Clusters!B:B)*(W26<=Clusters!C:C), 0))} -> 6
A27: Web Developer | B27: IT | C27: 59000 | D27: 3 | E27: 5 | F27: 2 | G27: 2 | H27: 1 | I27: 1 | J27: 1 | K27: 3 | L27: 1 | M27: 1 | N27: =INDEX('Points Schedule'!$H$3:$M$3, MATCH(D27, 'Points Schedule'!$H$2:$M$2, 0)) -> 30 | O27: =INDEX('Points Schedule'!$H$4:$M$4, MATCH(E27, 'Points Schedule'!$H$2:$M$2, 0)) -> 75 | P27: =INDEX('Points Schedule'!$H$5:$M$5, MATCH(F27, 'Points Schedule'!$H$2:$M$2, 0)) -> 10 | Q27: =INDEX('Points Schedule'!$H$6:$M$6, MATCH(G27, 'Points Schedule'!$H$2:$M$2, 0)) -> 50 | R27: =INDEX('Points Schedule'!$H$7:$M$7, MATCH(I27, 'Points Schedule'!$H$2:$M$2, 0)) -> 10 | S27: =INDEX('Points Schedule'!$H$8:$M$8, MATCH(J27, 'Points Schedule'!$H$2:$M$2, 0)) -> 70 | T27: =INDEX('Points Schedule'!$H$9:$M$9, MATCH(K27, 'Points Schedule'!$H$2:$M$2, 0)) -> 60 | U27: =INDEX('Points Schedule'!$H$10:$M$10, MATCH(L27, 'Points Schedule'!$H$2:$M$2, 0)) -> 40 | V27: =INDEX('Points Schedule'!$H$11:$M$11, MATCH(M27, 'Points Schedule'!$H$2:$M$2, 0)) -> 30 | W27: =SUM(N27:V27) -> 375 | X27: {=INDEX(Clusters!A:A, MATCH(1, (W27>=Clusters!B:B)*(W27<=Clusters!C:C), 0))} -> 6
A28: Communications Specialist | B28: Marketing | C28: 67040 | D28: 3 | E28: 3 | F28: 1 | G28: 1 | H28: 2 | I28: 1 | J28: 1 | K28: 2 | L28: 2 | M28: 3 | N28: =INDEX('Points Schedule'!$H$3:$M$3, MATCH(D28, 'Points Schedule'!$H$2:$M$2, 0)) -> 30 | O28: =INDEX('Points Schedule'!$H$4:$M$4, MATCH(E28, 'Points Schedule'!$H$2:$M$2, 0)) -> 45 | P28: =INDEX('Points Schedule'!$H$5:$M$5, MATCH(F28, 'Points Schedule'!$H$2:$M$2, 0)) -> 5 | Q28: =INDEX('Points Schedule'!$H$6:$M$6, MATCH(G28, 'Points Schedule'!$H$2:$M$2, 0)) -> 25 | R28: =INDEX('Points Schedule'!$H$7:$M$7, MATCH(I28, 'Points Schedule'!$H$2:$M$2, 0)) -> 10 | S28: =INDEX('Points Schedule'!$H$8:$M$8, MATCH(J28, 'Points Schedule'!$H$2:$M$2, 0)) -> 70 | T28: =INDEX('Points Schedule'!$H$9:$M$9, MATCH(K28, 'Points Schedule'!$H$2:$M$2, 0)) -> 40 | U28: =INDEX('Points Schedule'!$H$10:$M$10, MATCH(L28, 'Points Schedule'!$H$2:$M$2, 0)) -> 80 | V28: =INDEX('Points Schedule'!$H$11:$M$11, MATCH(M28, 'Points Schedule'!$H$2:$M$2, 0)) -> 90 | W28: =SUM(N28:V28) -> 395 | X28: {=INDEX(Clusters!A:A, MATCH(1, (W28>=Clusters!B:B)*(W28<=Clusters!C:C), 0))} -> 6 | Y28: 57.876923 | Z28: =Y28*1000 -> 57876.923
A29: Senior Accountant | B29: Ops | C29: 51082 | D29: 3 | E29: 2 | F29: 2 | G29: 2 | H29: 1 | I29: 3 | J29: 2 | K29: 1 | L29: 1 | M29: 2 | N29: =INDEX('Points Schedule'!$H$3:$M$3, MATCH(D29, 'Points Schedule'!$H$2:$M$2, 0)) -> 30 | O29: =INDEX('Points Schedule'!$H$4:$M$4, MATCH(E29, 'Points Schedule'!$H$2:$M$2, 0)) -> 30 | P29: =INDEX('Points Schedule'!$H$5:$M$5, MATCH(F29, 'Points Schedule'!$H$2:$M$2, 0)) -> 10 | Q29: =INDEX('Points Schedule'!$H$6:$M$6, MATCH(G29, 'Points Schedule'!$H$2:$M$2, 0)) -> 50 | R29: =INDEX('Points Schedule'!$H$7:$M$7, MATCH(I29, 'Points Schedule'!$H$2:$M$2, 0)) -> 30 | S29: =INDEX('Points Schedule'!$H$8:$M$8, MATCH(J29, 'Points Schedule'!$H$2:$M$2, 0)) -> 140 | T29: =INDEX('Points Schedule'!$H$9:$M$9, MATCH(K29, 'Points Schedule'!$H$2:$M$2, 0)) -> 20 | U29: =INDEX('Points Schedule'!$H$10:$M$10, MATCH(L29, 'Points Schedule'!$H$2:$M$2, 0)) -> 40 | V29: =INDEX('Points Schedule'!$H$11:$M$11, MATCH(M29, 'Points Schedule'!$H$2:$M$2, 0)) -> 60 | W29: =SUM(N29:V29) -> 410 | X29: {=INDEX(Clusters!A:A, MATCH(1, (W29>=Clusters!B:B)*(W29<=Clusters!C:C), 0))} -> 6 | Y29: 68.414634 | Z29: =Y29*1000 -> 68414.634
A30: Coordinator, Audit and Assurance | B30: Quality Assurance | C30: 64755 | D30: 3 | E30: 3 | F30: 2 | G30: 2 | H30: 2 | I30: 1 | J30: 1 | K30: 2 | L30: 2 | M30: 3 | N30: =INDEX('Points Schedule'!$H$3:$M$3, MATCH(D30, 'Points Schedule'!$H$2:$M$2, 0)) -> 30 | O30: =INDEX('Points Schedule'!$H$4:$M$4, MATCH(E30, 'Points Schedule'!$H$2:$M$2, 0)) -> 45 | P30: =INDEX('Points Schedule'!$H$5:$M$5, MATCH(F30, 'Points Schedule'!$H$2:$M$2, 0)) -> 10 | Q30: =INDEX('Points Schedule'!$H$6:$M$6, MATCH(G30, 'Points Schedule'!$H$2:$M$2, 0)) -> 50 | R30: =INDEX('Points Schedule'!$H$7:$M$7, MATCH(I30, 'Points Schedule'!$H$2:$M$2, 0)) -> 10 | S30: =INDEX('Points Schedule'!$H$8:$M$8, MATCH(J30, 'Points Schedule'!$H$2:$M$2, 0)) -> 70 | T30: =INDEX('Points Schedule'!$H$9:$M$9, MATCH(K30, 'Points Schedule'!$H$2:$M$2, 0)) -> 40 | U30: =INDEX('Points Schedule'!$H$10:$M$10, MATCH(L30, 'Points Schedule'!$H$2:$M$2, 0)) -> 80 | V30: =INDEX('Points Schedule'!$H$11:$M$11, MATCH(M30, 'Points Schedule'!$H$2:$M$2, 0)) -> 90 | W30: =SUM(N30:V30) -> 425 | X30: {=INDEX(Clusters!A:A, MATCH(1, (W30>=Clusters!B:B)*(W30<=Clusters!C:C), 0))} -> 7 | Y30: 70.516216 | Z30: =Y30*1000 -> 70516.216
A31: Marketing Coordinator | B31: Marketing | C31: 47375 | D31: 3 | E31: 3 | F31: 2 | G31: 2 | H31: 4 | I31: 3 | J31: 1 | K31: 3 | L31: 2 | M31: 3 | N31: =INDEX('Points Schedule'!$H$3:$M$3, MATCH(D31, 'Points Schedule'!$H$2:$M$2, 0)) -> 30 | O31: =INDEX('Points Schedule'!$H$4:$M$4, MATCH(E31, 'Points Schedule'!$H$2:$M$2, 0)) -> 45 | P31: =INDEX('Points Schedule'!$H$5:$M$5, MATCH(F31, 'Points Schedule'!$H$2:$M$2, 0)) -> 10 | Q31: =INDEX('Points Schedule'!$H$6:$M$6, MATCH(G31, 'Points Schedule'!$H$2:$M$2, 0)) -> 50 | R31: =INDEX('Points Schedule'!$H$7:$M$7, MATCH(I31, 'Points Schedule'!$H$2:$M$2, 0)) -> 30 | S31: =INDEX('Points Schedule'!$H$8:$M$8, MATCH(J31, 'Points Schedule'!$H$2:$M$2, 0)) -> 70 | T31: =INDEX('Points Schedule'!$H$9:$M$9, MATCH(K31, 'Points Schedule'!$H$2:$M$2, 0)) -> 60 | U31: =INDEX('Points Schedule'!$H$10:$M$10, MATCH(L31, 'Points Schedule'!$H$2:$M$2, 0)) -> 80 | V31: =INDEX('Points Schedule'!$H$11:$M$11, MATCH(M31, 'Points Schedule'!$H$2:$M$2, 0)) -> 90 | W31: =SUM(N31:V31) -> 465 | X31: {=INDEX(Clusters!A:A, MATCH(1, (W31>=Clusters!B:B)*(W31<=Clusters!C:C), 0))} -> 7 | Y31: 47.849333 | Z31: =Y31*1000 -> 47849.333
A32: Coordinator, Professional Programs | B32: Continuing Education | C32: 53042 | D32: 4 | E32: 3 | F32: 4 | G32: 2 | H32: 2 | I32: 1 | J32: 2 | K32: 4 | L32: 2 | M32: 2 | N32: =INDEX('Points Schedule'!$H$3:$M$3, MATCH(D32, 'Points Schedule'!$H$2:$M$2, 0)) -> 40 | O32: =INDEX('Points Schedule'!$H$4:$M$4, MATCH(E32, 'Points Schedule'!$H$2:$M$2, 0)) -> 45 | P32: =INDEX('Points Schedule'!$H$5:$M$5, MATCH(F32, 'Points Schedule'!$H$2:$M$2, 0)) -> 20 | Q32: =INDEX('Points Schedule'!$H$6:$M$6, MATCH(G32, 'Points Schedule'!$H$2:$M$2, 0)) -> 50 | R32: =INDEX('Points Schedule'!$H$7:$M$7, MATCH(I32, 'Points Schedule'!$H$2:$M$2, 0)) -> 10 | S32: =INDEX('Points Schedule'!$H$8:$M$8, MATCH(J32, 'Points Schedule'!$H$2:$M$2, 0)) -> 140 | T32: =INDEX('Points Schedule'!$H$9:$M$9, MATCH(K32, 'Points Schedule'!$H$2:$M$2, 0)) -> 80 | U32: =INDEX('Points Schedule'!$H$10:$M$10, MATCH(L32, 'Points Schedule'!$H$2:$M$2, 0)) -> 80 | V32: =INDEX('Points Schedule'!$H$11:$M$11, MATCH(M32, 'Points Schedule'!$H$2:$M$2, 0)) -> 60 | W32: =SUM(N32:V32) -> 525 | X32: {=INDEX(Clusters!A:A, MATCH(1, (W32>=Clusters!B:B)*(W32<=Clusters!C:C), 0))} -> 8
A33: Manager Conferences and Event Planning | B33: Continuing Education | C33: 72180 | D33: 2 | E33: 2 | F33: 4 | G33: 1 | H33: 4 | I33: 2 | J33: 3 | K33: 3 | L33: 2 | M33: 2 | N33: =INDEX('Points Schedule'!$H$3:$M$3, MATCH(D33, 'Points Schedule'!$H$2:$M$2, 0)) -> 20 | O33: =INDEX('Points Schedule'!$H$4:$M$4, MATCH(E33, 'Points Schedule'!$H$2:$M$2, 0)) -> 30 | P33: =INDEX('Points Schedule'!$H$5:$M$5, MATCH(F33, 'Points Schedule'!$H$2:$M$2, 0)) -> 20 | Q33: =INDEX('Points Schedule'!$H$6:$M$6, MATCH(G33, 'Points Schedule'!$H$2:$M$2, 0)) -> 25 | R33: =INDEX('Points Schedule'!$H$7:$M$7, MATCH(I33, 'Points Schedule'!$H$2:$M$2, 0)) -> 20 | S33: =INDEX('Points Schedule'!$H$8:$M$8, MATCH(J33, 'Points Schedule'!$H$2:$M$2, 0)) -> 210 | T33: =INDEX('Points Schedule'!$H$9:$M$9, MATCH(K33, 'Points Schedule'!$H$2:$M$2, 0)) -> 60 | U33: =INDEX('Points Schedule'!$H$10:$M$10, MATCH(L33, 'Points Schedule'!$H$2:$M$2, 0)) -> 80 | V33: =INDEX('Points Schedule'!$H$11:$M$11, MATCH(M33, 'Points Schedule'!$H$2:$M$2, 0)) -> 60 | W33: =SUM(N33:V33) -> 525 | X33: {=INDEX(Clusters!A:A, MATCH(1, (W33>=Clusters!B:B)*(W33<=Clusters!C:C), 0))} -> 8 | Y33: 69.642857 | Z33: =Y33*1000 -> 69642.857
A34: Manager, Workforce Recruitment | B34: Marketing | C34: 83828 | D34: 3 | E34: 5 | F34: 3 | G34: 3 | H34: 3 | I34: 2 | J34: 1 | K34: 4 | L34: 3 | M34: 2 | N34: =INDEX('Points Schedule'!$H$3:$M$3, MATCH(D34, 'Points Schedule'!$H$2:$M$2, 0)) -> 30 | O34: =INDEX('Points Schedule'!$H$4:$M$4, MATCH(E34, 'Points Schedule'!$H$2:$M$2, 0)) -> 75 | P34: =INDEX('Points Schedule'!$H$5:$M$5, MATCH(F34, 'Points Schedule'!$H$2:$M$2, 0)) -> 15 | Q34: =INDEX('Points Schedule'!$H$6:$M$6, MATCH(G34, 'Points Schedule'!$H$2:$M$2, 0)) -> 75 | R34: =INDEX('Points Schedule'!$H$7:$M$7, MATCH(I34, 'Points Schedule'!$H$2:$M$2, 0)) -> 20 | S34: =INDEX('Points Schedule'!$H$8:$M$8, MATCH(J34, 'Points Schedule'!$H$2:$M$2, 0)) -> 70 | T34: =INDEX('Points Schedule'!$H$9:$M$9, MATCH(K34, 'Points Schedule'!$H$2:$M$2, 0)) -> 80 | U34: =INDEX('Points Schedule'!$H$10:$M$10, MATCH(L34, 'Points Schedule'!$H$2:$M$2, 0)) -> 120 | V34: =INDEX('Points Schedule'!$H$11:$M$11, MATCH(M34, 'Points Schedule'!$H$2:$M$2, 0)) -> 60 | W34: =SUM(N34:V34) -> 545 | X34: {=INDEX(Clusters!A:A, MATCH(1, (W34>=Clusters!B:B)*(W34<=Clusters!C:C), 0))} -> 8
A35: Manager, Education Outreach | B35: Marketing | C35: 81247 | D35: 3 | E35: 2 | F35: 2 | G35: 3 | H35: 3 | I35: 2 | J35: 2 | K35: 4 | L35: 3 | M35: 2 | N35: =INDEX('Points Schedule'!$H$3:$M$3, MATCH(D35, 'Points Schedule'!$H$2:$M$2, 0)) -> 30 | O35: =INDEX('Points Schedule'!$H$4:$M$4, MATCH(E35, 'Points Schedule'!$H$2:$M$2, 0)) -> 30 | P35: =INDEX('Points Schedule'!$H$5:$M$5, MATCH(F35, 'Points Schedule'!$H$2:$M$2, 0)) -> 10 | Q35: =INDEX('Points Schedule'!$H$6:$M$6, MATCH(G35, 'Points Schedule'!$H$2:$M$2, 0)) -> 75 | R35: =INDEX('Points Schedule'!$H$7:$M$7, MATCH(I35, 'Points Schedule'!$H$2:$M$2, 0)) -> 20 | S35: =INDEX('Points Schedule'!$H$8:$M$8, MATCH(J35, 'Points Schedule'!$H$2:$M$2, 0)) -> 140 | T35: =INDEX('Points Schedule'!$H$9:$M$9, MATCH(K35, 'Points Schedule'!$H$2:$M$2, 0)) -> 80 | U35: =INDEX('Points Schedule'!$H$10:$M$10, MATCH(L35, 'Points Schedule'!$H$2:$M$2, 0)) -> 120 | V35: =INDEX('Points Schedule'!$H$11:$M$11, MATCH(M35, 'Points Schedule'!$H$2:$M$2, 0)) -> 60 | W35: =SUM(N35:V35) -> 565 | X35: {=INDEX(Clusters!A:A, MATCH(1, (W35>=Clusters!B:B)*(W35<=Clusters!C:C), 0))} -> 8
A36: Manager Finance and Administration | B36: Ops | C36: 69733 | D36: 3 | E36: 3 | F36: 3 | G36: 3 | H36: 5 | I36: 3 | J36: 2 | K36: 3 | L36: 2 | M36: 3 | N36: =INDEX('Points Schedule'!$H$3:$M$3, MATCH(D36, 'Points Schedule'!$H$2:$M$2, 0)) -> 30 | O36: =INDEX('Points Schedule'!$H$4:$M$4, MATCH(E36, 'Points Schedule'!$H$2:$M$2, 0)) -> 45 | P36: =INDEX('Points Schedule'!$H$5:$M$5, MATCH(F36, 'Points Schedule'!$H$2:$M$2, 0)) -> 15 | Q36: =INDEX('Points Schedule'!$H$6:$M$6, MATCH(G36, 'Points Schedule'!$H$2:$M$2, 0)) -> 75 | R36: =INDEX('Points Schedule'!$H$7:$M$7, MATCH(I36, 'Points Schedule'!$H$2:$M$2, 0)) -> 30 | S36: =INDEX('Points Schedule'!$H$8:$M$8, MATCH(J36, 'Points Schedule'!$H$2:$M$2, 0)) -> 140 | T36: =INDEX('Points Schedule'!$H$9:$M$9, MATCH(K36, 'Points Schedule'!$H$2:$M$2, 0)) -> 60 | U36: =INDEX('Points Schedule'!$H$10:$M$10, MATCH(L36, 'Points Schedule'!$H$2:$M$2, 0)) -> 80 | V36: =INDEX('Points Schedule'!$H$11:$M$11, MATCH(M36, 'Points Schedule'!$H$2:$M$2, 0)) -> 90 | W36: =SUM(N36:V36) -> 565 | X36: {=INDEX(Clusters!A:A, MATCH(1, (W36>=Clusters!B:B)*(W36<=Clusters!C:C), 0))} -> 8 | Y36: 85.162369 | Z36: =Y36*1000 -> 85162.369
A37: Manager, Executive Office | B37: Exec | C37: 71707 | D37: 3 | E37: 3 | F37: 4 | G37: 3 | H37: 4 | I37: 3 | J37: 2 | K37: 5 | L37: 3 | M37: 3 | N37: =INDEX('Points Schedule'!$H$3:$M$3, MATCH(D37, 'Points Schedule'!$H$2:$M$2, 0)) -> 30 | O37: =INDEX('Points Schedule'!$H$4:$M$4, MATCH(E37, 'Points Schedule'!$H$2:$M$2, 0)) -> 45 | P37: =INDEX('Points Schedule'!$H$5:$M$5, MATCH(F37, 'Points Schedule'!$H$2:$M$2, 0)) -> 20 | Q37: =INDEX('Points Schedule'!$H$6:$M$6, MATCH(G37, 'Points Schedule'!$H$2:$M$2, 0)) -> 75 | R37: =INDEX('Points Schedule'!$H$7:$M$7, MATCH(I37, 'Points Schedule'!$H$2:$M$2, 0)) -> 30 | S37: =INDEX('Points Schedule'!$H$8:$M$8, MATCH(J37, 'Points Schedule'!$H$2:$M$2, 0)) -> 140 | T37: =INDEX('Points Schedule'!$H$9:$M$9, MATCH(K37, 'Points Schedule'!$H$2:$M$2, 0)) -> 100 | U37: =INDEX('Points Schedule'!$H$10:$M$10, MATCH(L37, 'Points Schedule'!$H$2:$M$2, 0)) -> 120 | V37: =INDEX('Points Schedule'!$H$11:$M$11, MATCH(M37, 'Points Schedule'!$H$2:$M$2, 0)) -> 90 | W37: =SUM(N37:V37) -> 650 | X37: {=INDEX(Clusters!A:A, MATCH(1, (W37>=Clusters!B:B)*(W37<=Clusters!C:C), 0))} -> 9
A38: Manager, Audit and Assurance | B38: Quality Assurance | C38: 84980 | D38: 4 | E38: 5 | F38: 3 | G38: 3 | H38: 5 | I38: 1 | J38: 3 | K38: 3 | L38: 2 | M38: 3 | N38: =INDEX('Points Schedule'!$H$3:$M$3, MATCH(D38, 'Points Schedule'!$H$2:$M$2, 0)) -> 40 | O38: =INDEX('Points Schedule'!$H$4:$M$4, MATCH(E38, 'Points Schedule'!$H$2:$M$2, 0)) -> 75 | P38: =INDEX('Points Schedule'!$H$5:$M$5, MATCH(F38, 'Points Schedule'!$H$2:$M$2, 0)) -> 15 | Q38: =INDEX('Points Schedule'!$H$6:$M$6, MATCH(G38, 'Points Schedule'!$H$2:$M$2, 0)) -> 75 | R38: =INDEX('Points Schedule'!$H$7:$M$7, MATCH(I38, 'Points Schedule'!$H$2:$M$2, 0)) -> 10 | S38: =INDEX('Points Schedule'!$H$8:$M$8, MATCH(J38, 'Points Schedule'!$H$2:$M$2, 0)) -> 210 | T38: =INDEX('Points Schedule'!$H$9:$M$9, MATCH(K38, 'Points Schedule'!$H$2:$M$2, 0)) -> 60 | U38: =INDEX('Points Schedule'!$H$10:$M$10, MATCH(L38, 'Points Schedule'!$H$2:$M$2, 0)) -> 80 | V38: =INDEX('Points Schedule'!$H$11:$M$11, MATCH(M38, 'Points Schedule'!$H$2:$M$2, 0)) -> 90 | W38: =SUM(N38:V38) -> 655 | X38: {=INDEX(Clusters!A:A, MATCH(1, (W38>=Clusters!B:B)*(W38<=Clusters!C:C), 0))} -> 9
A39: Manager, Tax Quality | B39: Quality Assurance | C39: 70000 | D39: 4 | E39: 5 | F39: 3 | G39: 3 | H39: 5 | I39: 1 | J39: 3 | K39: 3 | L39: 2 | M39: 3 | N39: =INDEX('Points Schedule'!$H$3:$M$3, MATCH(D39, 'Points Schedule'!$H$2:$M$2, 0)) -> 40 | O39: =INDEX('Points Schedule'!$H$4:$M$4, MATCH(E39, 'Points Schedule'!$H$2:$M$2, 0)) -> 75 | P39: =INDEX('Points Schedule'!$H$5:$M$5, MATCH(F39, 'Points Schedule'!$H$2:$M$2, 0)) -> 15 | Q39: =INDEX('Points Schedule'!$H$6:$M$6, MATCH(G39, 'Points Schedule'!$H$2:$M$2, 0)) -> 75 | R39: =INDEX('Points Schedule'!$H$7:$M$7, MATCH(I39, 'Points Schedule'!$H$2:$M$2, 0)) -> 10 | S39: =INDEX('Points Schedule'!$H$8:$M$8, MATCH(J39, 'Points Schedule'!$H$2:$M$2, 0)) -> 210 | T39: =INDEX('Points Schedule'!$H$9:$M$9, MATCH(K39, 'Points Schedule'!$H$2:$M$2, 0)) -> 60 | U39: =INDEX('Points Schedule'!$H$10:$M$10, MATCH(L39, 'Points Schedule'!$H$2:$M$2, 0)) -> 80 | V39: =INDEX('Points Schedule'!$H$11:$M$11, MATCH(M39, 'Points Schedule'!$H$2:$M$2, 0)) -> 90 | W39: =SUM(N39:V39) -> 655 | X39: {=INDEX(Clusters!A:A, MATCH(1, (W39>=Clusters!B:B)*(W39<=Clusters!C:C), 0))} -> 9
A40: Manager, Member Services Centre | B40: Ops | C40: 95151 | D40: 4 | E40: 3 | F40: 4 | G40: 3 | H40: 5 | I40: 3 | J40: 3 | K40: 4 | L40: 2 | M40: 3 | N40: =INDEX('Points Schedule'!$H$3:$M$3, MATCH(D40, 'Points Schedule'!$H$2:$M$2, 0)) -> 40 | O40: =INDEX('Points Schedule'!$H$4:$M$4, MATCH(E40, 'Points Schedule'!$H$2:$M$2, 0)) -> 45 | P40: =INDEX('Points Schedule'!$H$5:$M$5, MATCH(F40, 'Points Schedule'!$H$2:$M$2, 0)) -> 20 | Q40: =INDEX('Points Schedule'!$H$6:$M$6, MATCH(G40, 'Points Schedule'!$H$2:$M$2, 0)) -> 75 | R40: =INDEX('Points Schedule'!$H$7:$M$7, MATCH(I40, 'Points Schedule'!$H$2:$M$2, 0)) -> 30 | S40: =INDEX('Points Schedule'!$H$8:$M$8, MATCH(J40, 'Points Schedule'!$H$2:$M$2, 0)) -> 210 | T40: =INDEX('Points Schedule'!$H$9:$M$9, MATCH(K40, 'Points Schedule'!$H$2:$M$2, 0)) -> 80 | U40: =INDEX('Points Schedule'!$H$10:$M$10, MATCH(L40, 'Points Schedule'!$H$2:$M$2, 0)) -> 80 | V40: =INDEX('Points Schedule'!$H$11:$M$11, MATCH(M40, 'Points Schedule'!$H$2:$M$2, 0)) -> 90 | W40: =SUM(N40:V40) -> 670 | X40: {=INDEX(Clusters!A:A, MATCH(1, (W40>=Clusters!B:B)*(W40<=Clusters!C:C), 0))} -> 9
A41: Director, IT | B41: IT | C41: 101981 | D41: 3 | E41: 3 | F41: 5 | G41: 3 | H41: 5 | I41: 3 | J41: 3 | K41: 3 | L41: 3 | M41: 3 | N41: =INDEX('Points Schedule'!$H$3:$M$3, MATCH(D41, 'Points Schedule'!$H$2:$M$2, 0)) -> 30 | O41: =INDEX('Points Schedule'!$H$4:$M$4, MATCH(E41, 'Points Schedule'!$H$2:$M$2, 0)) -> 45 | P41: =INDEX('Points Schedule'!$H$5:$M$5, MATCH(F41, 'Points Schedule'!$H$2:$M$2, 0)) -> 25 | Q41: =INDEX('Points Schedule'!$H$6:$M$6, MATCH(G41, 'Points Schedule'!$H$2:$M$2, 0)) -> 75 | R41: =INDEX('Points Schedule'!$H$7:$M$7, MATCH(I41, 'Points Schedule'!$H$2:$M$2, 0)) -> 30 | S41: =INDEX('Points Schedule'!$H$8:$M$8, MATCH(J41, 'Points Schedule'!$H$2:$M$2, 0)) -> 210 | T41: =INDEX('Points Schedule'!$H$9:$M$9, MATCH(K41, 'Points Schedule'!$H$2:$M$2, 0)) -> 60 | U41: =INDEX('Points Schedule'!$H$10:$M$10, MATCH(L41, 'Points Schedule'!$H$2:$M$2, 0)) -> 120 | V41: =INDEX('Points Schedule'!$H$11:$M$11, MATCH(M41, 'Points Schedule'!$H$2:$M$2, 0)) -> 90 | W41: =SUM(N41:V41) -> 685 | X41: {=INDEX(Clusters!A:A, MATCH(1, (W41>=Clusters!B:B)*(W41<=Clusters!C:C), 0))} -> 9 | Y41: 150.07879 | Z41: =Y41*1000 -> 150078.79
A42: Director, Continuing Education | B42: Continuing Education | C42: 83860 | D42: 4 | E42: 3 | F42: 5 | G42: 4 | H42: 6 | I42: 2 | J42: 4 | K42: 4 | L42: 2 | M42: 3 | N42: =INDEX('Points Schedule'!$H$3:$M$3, MATCH(D42, 'Points Schedule'!$H$2:$M$2, 0)) -> 40 | O42: =INDEX('Points Schedule'!$H$4:$M$4, MATCH(E42, 'Points Schedule'!$H$2:$M$2, 0)) -> 45 | P42: =INDEX('Points Schedule'!$H$5:$M$5, MATCH(F42, 'Points Schedule'!$H$2:$M$2, 0)) -> 25 | Q42: =INDEX('Points Schedule'!$H$6:$M$6, MATCH(G42, 'Points Schedule'!$H$2:$M$2, 0)) -> 100 | R42: =INDEX('Points Schedule'!$H$7:$M$7, MATCH(I42, 'Points Schedule'!$H$2:$M$2, 0)) -> 20 | S42: =INDEX('Points Schedule'!$H$8:$M$8, MATCH(J42, 'Points Schedule'!$H$2:$M$2, 0)) -> 280 | T42: =INDEX('Points Schedule'!$H$9:$M$9, MATCH(K42, 'Points Schedule'!$H$2:$M$2, 0)) -> 80 | U42: =INDEX('Points Schedule'!$H$10:$M$10, MATCH(L42, 'Points Schedule'!$H$2:$M$2, 0)) -> 80 | V42: =INDEX('Points Schedule'!$H$11:$M$11, MATCH(M42, 'Points Schedule'!$H$2:$M$2, 0)) -> 90 | W42: =SUM(N42:V42) -> 760 | X42: {=INDEX(Clusters!A:A, MATCH(1, (W42>=Clusters!B:B)*(W42<=Clusters!C:C), 0))} -> 9
A43: Director, Quality Assurance | B43: Quality Assurance | C43: 114302 | D43: 4 | E43: 5 | F43: 5 | G43: 4 | H43: 6 | I43: 1 | J43: 4 | K43: 4 | L43: 2 | M43: 4 | N43: =INDEX('Points Schedule'!$H$3:$M$3, MATCH(D43, 'Points Schedule'!$H$2:$M$2, 0)) -> 40 | O43: =INDEX('Points Schedule'!$H$4:$M$4, MATCH(E43, 'Points Schedule'!$H$2:$M$2, 0)) -> 75 | P43: =INDEX('Points Schedule'!$H$5:$M$5, MATCH(F43, 'Points Schedule'!$H$2:$M$2, 0)) -> 25 | Q43: =INDEX('Points Schedule'!$H$6:$M$6, MATCH(G43, 'Points Schedule'!$H$2:$M$2, 0)) -> 100 | R43: =INDEX('Points Schedule'!$H$7:$M$7, MATCH(I43, 'Points Schedule'!$H$2:$M$2, 0)) -> 10 | S43: =INDEX('Points Schedule'!$H$8:$M$8, MATCH(J43, 'Points Schedule'!$H$2:$M$2, 0)) -> 280 | T43: =INDEX('Points Schedule'!$H$9:$M$9, MATCH(K43, 'Points Schedule'!$H$2:$M$2, 0)) -> 80 | U43: =INDEX('Points Schedule'!$H$10:$M$10, MATCH(L43, 'Points Schedule'!$H$2:$M$2, 0)) -> 80 | V43: =INDEX('Points Schedule'!$H$11:$M$11, MATCH(M43, 'Points Schedule'!$H$2:$M$2, 0)) -> 120 | W43: =SUM(N43:V43) -> 810 | X43: {=INDEX(Clusters!A:A, MATCH(1, (W43>=Clusters!B:B)*(W43<=Clusters!C:C), 0))} -> 10
A44: Director, Marketing and Communications | B44: Marketing | C44: 118571 | D44: 4 | E44: 5 | F44: 5 | G44: 4 | H44: 6 | I44: 3 | J44: 4 | K44: 5 | L44: 2 | M44: 3 | N44: =INDEX('Points Schedule'!$H$3:$M$3, MATCH(D44, 'Points Schedule'!$H$2:$M$2, 0)) -> 40 | O44: =INDEX('Points Schedule'!$H$4:$M$4, MATCH(E44, 'Points Schedule'!$H$2:$M$2, 0)) -> 75 | P44: =INDEX('Points Schedule'!$H$5:$M$5, MATCH(F44, 'Points Schedule'!$H$2:$M$2, 0)) -> 25 | Q44: =INDEX('Points Schedule'!$H$6:$M$6, MATCH(G44, 'Points Schedule'!$H$2:$M$2, 0)) -> 100 | R44: =INDEX('Points Schedule'!$H$7:$M$7, MATCH(I44, 'Points Schedule'!$H$2:$M$2, 0)) -> 30 | S44: =INDEX('Points Schedule'!$H$8:$M$8, MATCH(J44, 'Points Schedule'!$H$2:$M$2, 0)) -> 280 | T44: =INDEX('Points Schedule'!$H$9:$M$9, MATCH(K44, 'Points Schedule'!$H$2:$M$2, 0)) -> 100 | U44: =INDEX('Points Schedule'!$H$10:$M$10, MATCH(L44, 'Points Schedule'!$H$2:$M$2, 0)) -> 80 | V44: =INDEX('Points Schedule'!$H$11:$M$11, MATCH(M44, 'Points Schedule'!$H$2:$M$2, 0)) -> 90 | W44: =SUM(N44:V44) -> 820 | X44: {=INDEX(Clusters!A:A, MATCH(1, (W44>=Clusters!B:B)*(W44<=Clusters!C:C), 0))} -> 10 | Y44: 178.075 | Z44: =Y44*1000 -> 178075
A45: Director, Operations | B45: Ops | C45: 126947 | D45: 4 | E45: 4 | F45: 5 | G45: 4 | H45: 6 | I45: 3 | J45: 4 | K45: 5 | L45: 2 | M45: 4 | N45: =INDEX('Points Schedule'!$H$3:$M$3, MATCH(D45, 'Points Schedule'!$H$2:$M$2, 0)) -> 40 | O45: =INDEX('Points Schedule'!$H$4:$M$4, MATCH(E45, 'Points Schedule'!$H$2:$M$2, 0)) -> 60 | P45: =INDEX('Points Schedule'!$H$5:$M$5, MATCH(F45, 'Points Schedule'!$H$2:$M$2, 0)) -> 25 | Q45: =INDEX('Points Schedule'!$H$6:$M$6, MATCH(G45, 'Points Schedule'!$H$2:$M$2, 0)) -> 100 | R45: =INDEX('Points Schedule'!$H$7:$M$7, MATCH(I45, 'Points Schedule'!$H$2:$M$2, 0)) -> 30 | S45: =INDEX('Points Schedule'!$H$8:$M$8, MATCH(J45, 'Points Schedule'!$H$2:$M$2, 0)) -> 280 | T45: =INDEX('Points Schedule'!$H$9:$M$9, MATCH(K45, 'Points Schedule'!$H$2:$M$2, 0)) -> 100 | U45: =INDEX('Points Schedule'!$H$10:$M$10, MATCH(L45, 'Points Schedule'!$H$2:$M$2, 0)) -> 80 | V45: =INDEX('Points Schedule'!$H$11:$M$11, MATCH(M45, 'Points Schedule'!$H$2:$M$2, 0)) -> 120 | W45: =SUM(N45:V45) -> 835 | X45: {=INDEX(Clusters!A:A, MATCH(1, (W45>=Clusters!B:B)*(W45<=Clusters!C:C), 0))} -> 10
A46: Executive Director | B46: Exec | C46: 171619 | D46: 4 | E46: 6 | F46: 6 | G46: 5 | H46: 6 | I46: 4 | J46: 4 | K46: 5 | L46: 4 | M46: 4 | N46: =INDEX('Points Schedule'!$H$3:$M$3, MATCH(D46, 'Points Schedule'!$H$2:$M$2, 0)) -> 40 | O46: =INDEX('Points Schedule'!$H$4:$M$4, MATCH(E46, 'Points Schedule'!$H$2:$M$2, 0)) -> 90 | P46: =INDEX('Points Schedule'!$H$5:$M$5, MATCH(F46, 'Points Schedule'!$H$2:$M$2, 0)) -> 30 | Q46: =INDEX('Points Schedule'!$H$6:$M$6, MATCH(G46, 'Points Schedule'!$H$2:$M$2, 0)) -> 125 | R46: =INDEX('Points Schedule'!$H$7:$M$7, MATCH(I46, 'Points Schedule'!$H$2:$M$2, 0)) -> 40 | S46: =INDEX('Points Schedule'!$H$8:$M$8, MATCH(J46, 'Points Schedule'!$H$2:$M$2, 0)) -> 280 | T46: =INDEX('Points Schedule'!$H$9:$M$9, MATCH(K46, 'Points Schedule'!$H$2:$M$2, 0)) -> 100 | U46: =INDEX('Points Schedule'!$H$10:$M$10, MATCH(L46, 'Points Schedule'!$H$2:$M$2, 0)) -> 160 | V46: =INDEX('Points Schedule'!$H$11:$M$11, MATCH(M46, 'Points Schedule'!$H$2:$M$2, 0)) -> 120 | W46: =SUM(N46:V46) -> 985 | X46: {=INDEX(Clusters!A:A, MATCH(1, (W46>=Clusters!B:B)*(W46<=Clusters!C:C), 0))} -> 11 | Y46: 265.65484 | Z46: =Y46*1000 -> 265654.84

Sheet Benchmarks
A1: Position Title | B1: Department | C1: 2007 Salary | D1: Total Points | E1: Cluster | F1: Benchmark
A2: =Data!A4 -> Receptionist | B2: =Data!B4 -> Ops | C2: =Data!C4 -> 44526 | D2: =Data!W4 -> 260 | E2: =Data!X4 -> 2 | F2: =Data!Z4 -> 35287.9
A3: =Data!A3 -> Administrative Clerk | B3: =Data!B3 -> Quality Assurance | C3: =Data!C3 -> 36260 | D3: =Data!W3 -> 255 | E3: =Data!X3 -> 1 | F3: =Data!Z3 -> 38372.611
A4: =Data!A5 -> Administrative Clerk | B4: =Data!B5 -> Ops | C4: =Data!C5 -> 36113 | D4: =Data!W5 -> 265 | E4: =Data!X5 -> 2 | F4: =Data!Z5 -> 38372.611
A5: =Data!A6 -> Administrative Clerk | B5: =Data!B6 -> Ops | C5: =Data!C6 -> 32008 | D5: =Data!W6 -> 265 | E5: =Data!X6 -> 2 | F5: =Data!Z6 -> 38372.611
A6: =Data!A16 -> Administrative Clerk/mailroom clerk | B6: =Data!B16 -> Ops | C6: =Data!C16 -> 40429 | D6: =Data!W16 -> 310 | E6: =Data!X16 -> 4 | F6: =Data!Z16 -> 39200.926
A7: =Data!A14 -> Junior Accountant | B7: =Data!B14 -> Ops | C7: =Data!C14 -> 32810 | D7: =Data!W14 -> 295 | E7: =Data!X14 -> 4 | F7: =Data!Z14 -> 44119.737
A8: =Data!A11 -> Secretary (Director Continuing Education) | B8: =Data!B11 -> Continuing Education | C8: =Data!C11 -> 43898 | D8: =Data!W11 -> 285 | E8: =Data!X11 -> 3 | F8: =Data!Z11 -> 47838.276
A9: =Data!A21 -> Secretary (Director Operations) | B9: =Data!B21 -> Ops | C9: =Data!C21 -> 49508 | D9: =Data!W21 -> 350 | E9: =Data!X21 -> 5 | F9: =Data!Z21 -> 47838.276
A10: =Data!A31 -> Marketing Coordinator | B10: =Data!B31 -> Marketing | C10: =Data!C31 -> 47375 | D10: =Data!W31 -> 465 | E10: =Data!X31 -> 7 | F10: =Data!Z31 -> 47849.333
A11: =Data!A7 -> Meetings and District Programs Coordinator | B11: =Data!B7 -> Continuing Education | C11: =Data!C7 -> 42908 | D11: =Data!W7 -> 280 | E11: =Data!X7 -> 3 | F11: =Data!Z7 -> 50257.143
A12: =Data!A9 -> Seminar Coordinator | B12: =Data!B9 -> Continuing Education | C12: =Data!C9 -> 38513 | D12: =Data!W9 -> 280 | E12: =Data!X9 -> 3 | F12: =Data!Z9 -> 50257.143
A13: =Data!A10 -> Seminar Coordinator | B13: =Data!B10 -> Continuing Education | C13: =Data!C10 -> 37370 | D13: =Data!W10 -> 280 | E13: =Data!X10 -> 3 | F13: =Data!Z10 -> 50257.143
A14: =Data!A17 -> Accountant | B14: =Data!B17 -> Ops | C14: =Data!C17 -> 41530 | D14: =Data!W17 -> 330 | E14: =Data!X17 -> 5 | F14: =Data!Z17 -> 53229.843
A15: =Data!A13 -> Administrative Assistant, Exec Office | B15: =Data!B13 -> Exec | C15: =Data!C13 -> 37258 | D15: =Data!W13 -> 290 | E15: =Data!X13 -> 4 | F15: =Data!Z13 -> 55492.47
A16: =Data!A28 -> Communications Specialist | B16: =Data!B28 -> Marketing | C16: =Data!C28 -> 67040 | D16: =Data!W28 -> 395 | E16: =Data!X28 -> 6 | F16: =Data!Z28 -> 57876.923
A17: =Data!A29 -> Senior Accountant | B17: =Data!B29 -> Ops | C17: =Data!C29 -> 51082 | D17: =Data!W29 -> 410 | E17: =Data!X29 -> 6 | F17: =Data!Z29 -> 68414.634
A18: =Data!A33 -> Manager Conferences and Event Planning | B18: =Data!B33 -> Continuing Education | C18: =Data!C33 -> 72180 | D18: =Data!W33 -> 525 | E18: =Data!X33 -> 8 | F18: =Data!Z33 -> 69642.857
A19: =Data!A30 -> Coordinator, Audit and Assurance | B19: =Data!B30 -> Quality Assurance | C19: =Data!C30 -> 64755 | D19: =Data!W30 -> 425 | E19: =Data!X30 -> 7 | F19: =Data!Z30 -> 70516.216
A20: =Data!A36 -> Manager Finance and Administration | B20: =Data!B36 -> Ops | C20: =Data!C36 -> 69733 | D20: =Data!W36 -> 565 | E20: =Data!X36 -> 8 | F20: =Data!Z36 -> 85162.369
A21: =Data!A41 -> Director, IT | B21: =Data!B41 -> IT | C21: =Data!C41 -> 101981 | D21: =Data!W41 -> 685 | E21: =Data!X41 -> 9 | F21: =Data!Z41 -> 150078.79
A22: =Data!A44 -> Director, Marketing and Communications | B22: =Data!B44 -> Marketing | C22: =Data!C44 -> 118571 | D22: =Data!W44 -> 820 | E22: =Data!X44 -> 10 | F22: =Data!Z44 -> 178075
A23: =Data!A46 -> Executive Director | B23: =Data!B46 -> Exec | C23: =Data!C46 -> 171619 | D23: =Data!W46 -> 985 | E23: =Data!X46 -> 11 | F23: =Data!Z46 -> 265654.84
A24: =Data!A8 -> Circulation Technician & Receptionist | B24: =Data!B8 -> Ops | C24: =Data!C8 -> 46481 | D24: =Data!W8 -> 280 | E24: =Data!X8 -> 3
A25: =Data!A12 -> Junior Systems Administrator | B25: =Data!B12 -> IT | C25: =Data!C12 -> 41500 | D25: =Data!W12 -> 290 | E25: =Data!X12 -> 4
A26: =Data!A15 -> Business Research Coordinator | B26: =Data!B15 -> Ops | C26: =Data!C15 -> 58000 | D26: =Data!W15 -> 295 | E26: =Data!X15 -> 4
A27: =Data!A18 -> Programmer | B27: =Data!B18 -> IT | C27: =Data!C18 -> 77289 | D27: =Data!W18 -> 335 | E27: =Data!X18 -> 5
A28: =Data!A19 -> Career Consultant | B28: =Data!B19 -> Ops | C28: =Data!C19 -> 68700 | D28: =Data!W19 -> 340 | E28: =Data!X19 -> 5
A29: =Data!A20 -> Associate Coordinator, Professional Programs | B29: =Data!B20 -> Continuing Education | C29: =Data!C20 -> 39104 | D29: =Data!W20 -> 345 | E29: =Data!X20 -> 5
A30: =Data!A22 -> Business Analyst | B30: =Data!B22 -> Ops | C30: =Data!C22 -> 63348 | D30: =Data!W22 -> 350 | E30: =Data!X22 -> 5
A31: =Data!A23 -> Peer Review Administrator, Audit | B31: =Data!B23 -> Quality Assurance | C31: =Data!C23 -> 56000 | D31: =Data!W23 -> 355 | E31: =Data!X23 -> 5
A32: =Data!A24 -> Peer Review Administrator, Audit | B32: =Data!B24 -> Quality Assurance | C32: =Data!C24 -> 54390 | D32: =Data!W24 -> 355 | E32: =Data!X24 -> 5
A33: =Data!A25 -> Peer Review Administrator, Tax | B33: =Data!B25 -> Quality Assurance | C33: =Data!C25 -> 58700 | D33: =Data!W25 -> 360 | E33: =Data!X25 -> 5
A34: =Data!A26 -> Information Officer | B34: =Data!B26 -> Marketing | C34: =Data!C26 -> 55233 | D34: =Data!W26 -> 365 | E34: =Data!X26 -> 6
A35: =Data!A27 -> Web Developer | B35: =Data!B27 -> IT | C35: =Data!C27 -> 59000 | D35: =Data!W27 -> 375 | E35: =Data!X27 -> 6
A36: =Data!A32 -> Coordinator, Professional Programs | B36: =Data!B32 -> Continuing Education | C36: =Data!C32 -> 53042 | D36: =Data!W32 -> 525 | E36: =Data!X32 -> 8
A37: =Data!A34 -> Manager, Workforce Recruitment | B37: =Data!B34 -> Marketing | C37: =Data!C34 -> 83828 | D37: =Data!W34 -> 545 | E37: =Data!X34 -> 8
A38: =Data!A35 -> Manager, Education Outreach | B38: =Data!B35 -> Marketing | C38: =Data!C35 -> 81247 | D38: =Data!W35 -> 565 | E38: =Data!X35 -> 8
A39: =Data!A37 -> Manager, Executive Office | B39: =Data!B37 -> Exec | C39: =Data!C37 -> 71707 | D39: =Data!W37 -> 650 | E39: =Data!X37 -> 9
A40: =Data!A38 -> Manager, Audit and Assurance | B40: =Data!B38 -> Quality Assurance | C40: =Data!C38 -> 84980 | D40: =Data!W38 -> 655 | E40: =Data!X38 -> 9
A41: =Data!A39 -> Manager, Tax Quality | B41: =Data!B39 -> Quality Assurance | C41: =Data!C39 -> 70000 | D41: =Data!W39 -> 655 | E41: =Data!X39 -> 9
A42: =Data!A40 -> Manager, Member Services Centre | B42: =Data!B40 -> Ops | C42: =Data!C40 -> 95151 | D42: =Data!W40 -> 670 | E42: =Data!X40 -> 9
A43: =Data!A42 -> Director, Continuing Education | B43: =Data!B42 -> Continuing Education | C43: =Data!C42 -> 83860 | D43: =Data!W42 -> 760 | E43: =Data!X42 -> 9
A44: =Data!A43 -> Director, Quality Assurance | B44: =Data!B43 -> Quality Assurance | C44: =Data!C43 -> 114302 | D44: =Data!W43 -> 810 | E44: =Data!X43 -> 10
A45: =Data!A45 -> Director, Operations | B45: =Data!B45 -> Ops | C45: =Data!C45 -> 126947 | D45: =Data!W45 -> 835 | E45: =Data!X45 -> 10

Sheet Benchmark-Points Regression
A1: SUMMARY OUTPUT | N1: Position Title | O1: Department | P1: Total Points | Q1: Benchmark
N2: =Benchmarks!A2 -> Receptionist | O2: =Benchmarks!B2 -> Ops | P2: =Benchmarks!D2 -> 260 | Q2: =Benchmarks!F2 -> 35287.9
A3: Regression Statistics | N3: =Benchmarks!A3 -> Administrative Clerk | O3: =Benchmarks!B3 -> Quality Assurance | P3: =Benchmarks!D3 -> 255 | Q3: =Benchmarks!F3 -> 38372.611
A4: Multiple R | B4: 0.95116683 | N4: =Benchmarks!A4 -> Administrative Clerk | O4: =Benchmarks!B4 -> Ops | P4: =Benchmarks!D4 -> 265 | Q4: =Benchmarks!F4 -> 38372.611
A5: R Square | B5: 0.90471834 | N5: =Benchmarks!A5 -> Administrative Clerk | O5: =Benchmarks!B5 -> Ops | P5: =Benchmarks!D5 -> 265 | Q5: =Benchmarks!F5 -> 38372.611
A6: Adjusted R Square | B6: 0.89995426 | N6: =Benchmarks!A6 -> Administrative Clerk/mailroom clerk | O6: =Benchmarks!B6 -> Ops | P6: =Benchmarks!D6 -> 310 | Q6: =Benchmarks!F6 -> 39200.926
A7: Standard Error | B7: 17682.486 | N7: =Benchmarks!A7 -> Junior Accountant | O7: =Benchmarks!B7 -> Ops | P7: =Benchmarks!D7 -> 295 | Q7: =Benchmarks!F7 -> 44119.737
A8: Observations | B8: 22 | N8: =Benchmarks!A8 -> Secretary (Director Continuing Education) | O8: =Benchmarks!B8 -> Continuing Education | P8: =Benchmarks!D8 -> 285 | Q8: =Benchmarks!F8 -> 47838.276
N9: =Benchmarks!A9 -> Secretary (Director Operations) | O9: =Benchmarks!B9 -> Ops | P9: =Benchmarks!D9 -> 350 | Q9: =Benchmarks!F9 -> 47838.276
A10: ANOVA | N10: =Benchmarks!A10 -> Marketing Coordinator | O10: =Benchmarks!B10 -> Marketing | P10: =Benchmarks!D10 -> 465 | Q10: =Benchmarks!F10 -> 47849.333
B11: df | C11: SS | D11: MS | E11: F | F11: Significance F | N11: =Benchmarks!A11 -> Meetings and District Programs Coordinator | O11: =Benchmarks!B11 -> Continuing Education | P11: =Benchmarks!D11 -> 280 | Q11: =Benchmarks!F11 -> 50257.143
A12: Regression | B12: 1 | C12: 5.9377338e+10 | D12: 5.9377338e+10 | E12: 189.90399 | F12: 1.1370456e-11 | N12: =Benchmarks!A12 -> Seminar Coordinator | O12: =Benchmarks!B12 -> Continuing Education | P12: =Benchmarks!D12 -> 280 | Q12: =Benchmarks!F12 -> 50257.143
A13: Residual | B13: 20 | C13: 6.253406e+09 | D13: 3.126703e+08 | N13: =Benchmarks!A13 -> Seminar Coordinator | O13: =Benchmarks!B13 -> Continuing Education | P13: =Benchmarks!D13 -> 280 | Q13: =Benchmarks!F13 -> 50257.143
A14: Total | B14: 21 | C14: 6.5630744e+10 | N14: =Benchmarks!A14 -> Accountant | O14: =Benchmarks!B14 -> Ops | P14: =Benchmarks!D14 -> 330 | Q14: =Benchmarks!F14 -> 53229.843
N15: =Benchmarks!A15 -> Administrative Assistant, Exec Office | O15: =Benchmarks!B15 -> Exec | P15: =Benchmarks!D15 -> 290 | Q15: =Benchmarks!F15 -> 55492.47
B16: Coefficients | C16: Standard Error | D16: t Stat | E16: P-value | F16: Lower 95% | G16: Upper 95% | H16: Lower 95.0% | I16: Upper 95.0% | N16: =Benchmarks!A16 -> Communications Specialist | O16: =Benchmarks!B16 -> Marketing | P16: =Benchmarks!D16 -> 395 | Q16: =Benchmarks!F16 -> 57876.923
A17: Intercept | B17: -38573.493 | C17: 8859.9013 | D17: -4.3537159 | E17: 0.00030773095 | F17: -57054.924 | G17: -20092.063 | H17: -57054.924 | I17: -20092.063 | N17: =Benchmarks!A17 -> Senior Accountant | O17: =Benchmarks!B17 -> Ops | P17: =Benchmarks!D17 -> 410 | Q17: =Benchmarks!F17 -> 68414.634
A18: Total Points | B18: 269.4883 | C18: 19.555678 | D18: 13.780566 | E18: 1.1370456e-11 | F18: 228.69587 | G18: 310.28073 | H18: 228.69587 | I18: 310.28073 | N18: =Benchmarks!A18 -> Manager Conferences and Event Planning | O18: =Benchmarks!B18 -> Continuing Education | P18: =Benchmarks!D18 -> 525 | Q18: =Benchmarks!F18 -> 69642.857
N19: =Benchmarks!A19 -> Coordinator, Audit and Assurance | O19: =Benchmarks!B19 -> Quality Assurance | P19: =Benchmarks!D19 -> 425 | Q19: =Benchmarks!F19 -> 70516.216
N20: =Benchmarks!A20 -> Manager Finance and Administration | O20: =Benchmarks!B20 -> Ops | P20: =Benchmarks!D20 -> 565 | Q20: =Benchmarks!F20 -> 85162.369
N21: =Benchmarks!A21 -> Director, IT | O21: =Benchmarks!B21 -> IT | P21: =Benchmarks!D21 -> 685 | Q21: =Benchmarks!F21 -> 150078.79
N22: =Benchmarks!A22 -> Director, Marketing and Communications | O22: =Benchmarks!B22 -> Marketing | P22: =Benchmarks!D22 -> 820 | Q22: =Benchmarks!F22 -> 178075
N23: =Benchmarks!A23 -> Executive Director | O23: =Benchmarks!B23 -> Exec | P23: =Benchmarks!D23 -> 985 | Q23: =Benchmarks!F23 -> 265654.84

Sheet Internal-Points Regression
A1: SUMMARY OUTPUT | N1: Position Title | O1: Department | P1: Total Points | Q1: 2007 Salary
N2: Administrative Clerk | O2: Quality Assurance | P2: 255 | Q2: 36260
A3: Regression Statistics | N3: Receptionist | O3: Ops | P3: 260 | Q3: 44526
A4: Multiple R | B4: 0.91079235 | N4: Administrative Clerk | O4: Ops | P4: 265 | Q4: 36113
A5: R Square | B5: 0.82954271 | N5: Administrative Clerk | O5: Ops | P5: 265 | Q5: 32008
A6: Adjusted R Square | B6: 0.82548421 | N6: Circulation Technician & Receptionist | O6: Ops | P6: 280 | Q6: 46481
A7: Standard Error | B7: 12058.697 | N7: Meetings and District Programs Coordinator | O7: Continuing Education | P7: 280 | Q7: 42908
A8: Observations | B8: 44 | N8: Seminar Coordinator | O8: Continuing Education | P8: 280 | Q8: 38513
N9: Seminar Coordinator | O9: Continuing Education | P9: 280 | Q9: 37370
A10: ANOVA | N10: Secretary (Director Continuing Education) | O10: Continuing Education | P10: 285 | Q10: 43898
B11: df | C11: SS | D11: MS | E11: F | F11: Significance F | N11: Administrative Assistant, Exec Office | O11: Exec | P11: 290 | Q11: 37258
A12: Regression | B12: 1 | C12: 2.9721671e+10 | D12: 2.9721671e+10 | E12: 204.39604 | F12: 9.7775945e-18 | N12: Junior Systems Administrator | O12: IT | P12: 290 | Q12: 41500
A13: Residual | B13: 42 | C13: 6.1073112e+09 | D13: 1.4541217e+08 | N13: Business Research Coordinator | O13: Ops | P13: 295 | Q13: 58000
A14: Total | B14: 43 | C14: 3.5828983e+10 | N14: Junior Accountant | O14: Ops | P14: 295 | Q14: 32810
N15: Administrative Clerk/mailroom clerk | O15: Ops | P15: 310 | Q15: 40429
B16: Coefficients | C16: Standard Error | D16: t Stat | E16: P-value | F16: Lower 95% | G16: Upper 95% | H16: Lower 95.0% | I16: Upper 95.0% | N16: Accountant | O16: Ops | P16: 330 | Q16: 41530
A17: Intercept | B17: 2790.2867 | C17: 4657.6085 | D17: 0.59908142 | E17: 0.55233652 | F17: -6609.1477 | G17: 12189.721 | H17: -6609.1477 | I17: 12189.721 | N17: Programmer | O17: IT | P17: 335 | Q17: 77289
A18: Total Points | B18: 136.68626 | C18: 9.5606767 | D18: 14.296714 | E18: 9.7775945e-18 | F18: 117.39204 | G18: 155.98049 | H18: 117.39204 | I18: 155.98049 | N18: Career Consultant | O18: Ops | P18: 340 | Q18: 68700
N19: Associate Coordinator, Professional Programs | O19: Continuing Education | P19: 345 | Q19: 39104
N20: Business Analyst | O20: Ops | P20: 350 | Q20: 63348
N21: Secretary (Director Operations) | O21: Ops | P21: 350 | Q21: 49508
N22: Peer Review Administrator, Audit | O22: Quality Assurance | P22: 355 | Q22: 56000
N23: Peer Review Administrator, Audit | O23: Quality Assurance | P23: 355 | Q23: 54390
N24: Peer Review Administrator, Tax | O24: Quality Assurance | P24: 360 | Q24: 58700
N25: Information Officer | O25: Marketing | P25: 365 | Q25: 55233
N26: Web Developer | O26: IT | P26: 375 | Q26: 59000
N27: Communications Specialist | O27: Marketing | P27: 395 | Q27: 67040
N28: Senior Accountant | O28: Ops | P28: 410 | Q28: 51082
N29: Coordinator, Audit and Assurance | O29: Quality Assurance | P29: 425 | Q29: 64755
N30: Marketing Coordinator | O30: Marketing | P30: 465 | Q30: 47375
... N45: Executive Director | O45: Exec | P45: 985 | Q45: 171619

Sheet Pay Structure
A1: Grade | B1: Minimum | C1: Midpoint | D1: Maximum | F1: Midpoint Progression | G1: Midpoint Width | H1: Count
A2: 1 | B2: =C2*(1-G2) -> 24942.197 | C2: =AVERAGE(Data!Z3) -> 38372.611 | D2: =C2*(1+G2) -> 51803.025 | G2: 0.35 | H2: =COUNTIF(Data!X:X, A2) -> 1
A3: 2 | B3: =C3*(1-G3) -> 27935.261 | C3: =C2*(1+F3) -> 42977.325 | D3: =C3*(1+G3) -> 58019.389 | F3: 0.12 | G3: 0.35 | H3: =COUNTIF(Data!X:X, A3) -> 3
A4: 3 | B4: =C4*(1-G4) -> 31287.492 | C4: =C3*(1+F4) -> 48134.604 | D4: =C4*(1+G4) -> 64981.715 | F4: 0.12 | G4: 0.35 | H4: =COUNTIF(Data!X:X, A4) -> 5
A5: 4 | B5: =C5*(1-G5) -> 34416.242 | C5: =C4*(1+F5) -> 52948.064 | D5: =C5*(1+G5) -> 71479.887 | F5: 0.1 | G5: 0.35 | H5: =COUNTIF(Data!X:X, A5) -> 5
A6: 5 | B6: =C6*(1-G6) -> 38890.353 | C6: =C5*(1+F6) -> 59831.313 | D6: =C6*(1+G6) -> 80772.272 | F6: 0.13 | G6: 0.35 | H6: =COUNTIF(Data!X:X, A6) -> 9
A7: 6 | B7: =C7*(1-G7) -> 43168.292 | C7: =C6*(1+F7) -> 66412.757 | D7: =C7*(1+G7) -> 89657.222 | F7: 0.11 | G7: 0.35 | H7: =COUNTIF(Data!X:X, A7) -> 4
A8: 7 | B8: =C8*(1-G8) -> 44463.341 | C8: =C7*(1+F8) -> 68405.14 | D8: =C8*(1+G8) -> 92346.939 | F8: 0.03 | G8: 0.35 | H8: =COUNTIF(Data!X:X, A8) -> 2
A9: 8 | B9: =C9*(1-G9) -> 49354.308 | C9: =C8*(1+F9) -> 75929.705 | D9: =C9*(1+G9) -> 102505.1 | F9: 0.11 | G9: 0.35 | H9: =COUNTIF(Data!X:X, A9) -> 5
A10: 9 | B10: =C10*(1-G10) -> 56757.454 | C10: =C9*(1+F10) -> 87319.161 | D10: =C10*(1+G10) -> 117880.87 | F10: 0.15 | G10: 0.35 | H10: =COUNTIF(Data!X:X, A10) -> 6
A11: 10 | B11: =C11*(1-G11) -> 65271.073 | C11: =C10*(1+F11) -> 100417.03 | D11: =C11*(1+G11) -> 135563 | F11: 0.15 | G11: 0.35 | H11: =COUNTIF(Data!X:X, A11) -> 3
A12: 11 | B12: =C12*(1-G12) -> 57739.795 | C12: =C11*(1+F12) -> 115479.59 | D12: =C12*(1+G12) -> 173219.39 | F12: 0.15 | G12: 0.5 | H12: =COUNTIF(Data!X:X, A12) -> 1
C14: Total Weighted Sum: | D14: =SUMPRODUCT(D2:D12,H2:H12) -> 3978161.5

Sheet Internal Compa-ratios
A1: Position Title | B1: Department | C1: 2007 Salary | D1: Grade | E1: Proposed Midpoint | F1: Compa-Ratio | G1: Compa-Grade Average | H1: Midpoint Width | I1: Salary Adjustment
A2: =Data!A3 -> Administrative Clerk | B2: =Data!B3 -> Quality Assurance | C2: =Data!C3 -> 36260 | D2: =Data!X3 -> 1 | E2: =VLOOKUP(D2, 'Pay Structure'!$A$1:$D$12, 3, FALSE) -> 38372.611 | F2: =C2/E2 -> 0.94494481 | G2: =F2 -> 0.94494481 | H2: =VLOOKUP(D2, 'Pay Structure'!$A$1:$G$12, 7, FALSE) -> 0.35 | I2: 0
A3: =Data!A4 -> Receptionist | B3: =Data!B4 -> Ops | C3: =Data!C4 -> 44526 | D3: =Data!X4 -> 2 | E3: =VLOOKUP(D3, 'Pay Structure'!$A$1:$D$12, 3, FALSE) -> 42977.325 | F3: =C3/E3 -> 1.0360347 | H3: =VLOOKUP(D3, 'Pay Structure'!$A$1:$G$12, 7, FALSE) -> 0.35 | I3: 0
A4: =Data!A5 -> Administrative Clerk | B4: =Data!B5 -> Ops | C4: =Data!C5 -> 36113 | D4: =Data!X5 -> 2 | E4: =VLOOKUP(D4, 'Pay Structure'!$A$1:$D$12, 3, FALSE) -> 42977.325 | F4: =C4/E4 -> 0.84028031 | H4: =VLOOKUP(D4, 'Pay Structure'!$A$1:$G$12, 7, FALSE) -> 0.35 | I4: 0
A5: =Data!A6 -> Administrative Clerk | B5: =Data!B6 -> Ops | C5: =Data!C6 -> 32008 | D5: =Data!X6 -> 2 | E5: =VLOOKUP(D5, 'Pay Structure'!$A$1:$D$12, 3, FALSE) -> 42977.325 | F5: =C5/E5 -> 0.74476483 | G5: =AVERAGE(F3:F5) -> 0.87369328 | H5: =VLOOKUP(D5, 'Pay Structure'!$A$1:$G$12, 7, FALSE) -> 0.35 | I5: 0
A6: =Data!A7 -> Meetings and District Programs Coordinator | B6: =Data!B7 -> Continuing Education | C6: =Data!C7 -> 42908 | D6: =Data!X7 -> 3 | E6: =VLOOKUP(D6, 'Pay Structure'!$A$1:$D$12, 3, FALSE) -> 48134.604 | F6: =C6/E6 -> 0.89141691 | H6: =VLOOKUP(D6, 'Pay Structure'!$A$1:$G$12, 7, FALSE) -> 0.35 | I6: 0
A7: =Data!A8 -> Circulation Technician & Receptionist | B7: =Data!B8 -> Ops | C7: =Data!C8 -> 46481 | D7: =Data!X8 -> 3 | E7: =VLOOKUP(D7, 'Pay Structure'!$A$1:$D$12, 3, FALSE) -> 48134.604 | F7: =C7/E7 -> 0.96564626 | H7: =VLOOKUP(D7, 'Pay Structure'!$A$1:$G$12, 7, FALSE) -> 0.35 | I7: 0
A8: =Data!A9 -> Seminar Coordinator | B8: =Data!B9 -> Continuing Education | C8: =Data!C9 -> 38513 | D8: =Data!X9 -> 3 | E8: =VLOOKUP(D8, 'Pay Structure'!$A$1:$D$12, 3, FALSE) -> 48134.604 | F8: =C8/E8 -> 0.80011046 | H8: =VLOOKUP(D8, 'Pay Structure'!$A$1:$G$12, 7, FALSE) -> 0.35 | I8: 0
A9: =Data!A10 -> Seminar Coordinator | B9: =Data!B10 -> Continuing Education | C9: =Data!C10 -> 37370 | D9: =Data!X10 -> 3 | E9: =VLOOKUP(D9, 'Pay Structure'!$A$1:$D$12, 3, FALSE) -> 48134.604 | F9: =C9/E9 -> 0.77636455 | H9: =VLOOKUP(D9, 'Pay Structure'!$A$1:$G$12, 7, FALSE) -> 0.35 | I9: 0
A10: =Data!A11 -> Secretary (Director Continuing Education) | B10: =Data!B11 -> Continuing Education | C10: =Data!C11 -> 43898 | D10: =Data!X11 -> 3 | E10: =VLOOKUP(D10, 'Pay Structure'!$A$1:$D$12, 3, FALSE) -> 48134.604 | F10: =C10/E10 -> 0.91198424 | G10: =AVERAGE(F6:F10) -> 0.86910448 | H10: =VLOOKUP(D10, 'Pay Structure'!$A$1:$G$12, 7, FALSE) -> 0.35 | I10: 0
A11: =Data!A12 -> Junior Systems Administrator | B11: =Data!B12 -> IT | C11: =Data!C12 -> 41500 | D11: =Data!X12 -> 4 | E11: =VLOOKUP(D11, 'Pay Structure'!$A$1:$D$12, 3, FALSE) -> 52948.064 | F11: =C11/E11 -> 0.78378692 | H11: =VLOOKUP(D11, 'Pay Structure'!$A$1:$G$12, 7, FALSE) -> 0.35 | I11: 0
A12: =Data!A13 -> Administrative Assistant, Exec Office | B12: =Data!B13 -> Exec | C12: =Data!C13 -> 37258 | D12: =Data!X13 -> 4 | E12: =VLOOKUP(D12, 'Pay Structure'!$A$1:$D$12, 3, FALSE) -> 52948.064 | F12: =C12/E12 -> 0.70367067 | H12: =VLOOKUP(D12, 'Pay Structure'!$A$1:$G$12, 7, FALSE) -> 0.35 | I12: 0
A13: =Data!A14 -> Junior Accountant | B13: =Data!B14 -> Ops | C13: =Data!C14 -> 32810 | D13: =Data!X14 -> 4 | E13: =VLOOKUP(D13, 'Pay Structure'!$A$1:$D$12, 3, FALSE) -> 52948.064 | F13: =C13/E13 -> 0.61966383 | H13: =VLOOKUP(D13, 'Pay Structure'!$A$1:$G$12, 7, FALSE) -> 0.35 | I13: ='Pay Structure'!B5-'Internal Compa-ratios'!C13 -> 1606.2417
A14: =Data!A15 -> Business Research Coordinator | B14: =Data!B15 -> Ops | C14: =Data!C15 -> 58000 | D14: =Data!X15 -> 4 | E14: =VLOOKUP(D14, 'Pay Structure'!$A$1:$D$12, 3, FALSE) -> 52948.064 | F14: =C14/E14 -> 1.095413 | H14: =VLOOKUP(D14, 'Pay Structure'!$A$1:$G$12, 7, FALSE) -> 0.35 | I14: 0
A15: =Data!A16 -> Administrative Clerk/mailroom clerk | B15: =Data!B16 -> Ops | C15: =Data!C16 -> 40429 | D15: =Data!X16 -> 4 | E15: =VLOOKUP(D15, 'Pay Structure'!$A$1:$D$12, 3, FALSE) -> 52948.064 | F15: =C15/E15 -> 0.76355955 | G15: =AVERAGE(F11:F15) -> 0.7932188 | H15: =VLOOKUP(D15, 'Pay Structure'!$A$1:$G$12, 7, FALSE) -> 0.35 | I15: 0
A16: =Data!A17 -> Accountant | B16: =Data!B17 -> Ops | C16: =Data!C17 -> 41530 | D16: =Data!X17 -> 5 | E16: =VLOOKUP(D16, 'Pay Structure'!$A$1:$D$12, 3, FALSE) -> 59831.313 | F16: =C16/E16 -> 0.69411815 | H16: =VLOOKUP(D16, 'Pay Structure'!$A$1:$G$12, 7, FALSE) -> 0.35 | I16: 0
A17: =Data!A18 -> Programmer | B17: =Data!B18 -> IT | C17: =Data!C18 -> 77289 | D17: =Data!X18 -> 5 | E17: =VLOOKUP(D17, 'Pay Structure'!$A$1:$D$12, 3, FALSE) -> 59831.313 | F17: =C17/E17 -> 1.2917818 | H17: =VLOOKUP(D17, 'Pay Structure'!$A$1:$G$12, 7, FALSE) -> 0.35 | I17: 0
A18: =Data!A19 -> Career Consultant | B18: =Data!B19 -> Ops | C18: =Data!C19 -> 68700 | D18: =Data!X19 -> 5 | E18: =VLOOKUP(D18, 'Pay Structure'!$A$1:$D$12, 3, FALSE) -> 59831.313 | F18: =C18/E18 -> 1.1482282 | H18: =VLOOKUP(D18, 'Pay Structure'!$A$1:$G$12, 7, FALSE) -> 0.35 | I18: 0
A19: =Data!A20 -> Associate Coordinator, Professional Programs | B19: =Data!B20 -> Continuing Education | C19: =Data!C20 -> 39104 | D19: =Data!X20 -> 5 | E19: =VLOOKUP(D19, 'Pay Structure'!$A$1:$D$12, 3, FALSE) -> 59831.313 | F19: =C19/E19 -> 0.65357082 | H19: =VLOOKUP(D19, 'Pay Structure'!$A$1:$G$12, 7, FALSE) -> 0.35 | I19: 0
A20: =Data!A21 -> Secretary (Director Operations) | B20: =Data!B21 -> Ops | C20: =Data!C21 -> 49508 | D20: =Data!X21 -> 5 | E20: =VLOOKUP(D20, 'Pay Structure'!$A$1:$D$12, 3, FALSE) -> 59831.313 | F20: =C20/E20 -> 0.8274597 | H20: =VLOOKUP(D20, 'Pay Structure'!$A$1:$G$12, 7, FALSE) -> 0.35 | I20: 0
A21: =Data!A22 -> Business Analyst | B21: =Data!B22 -> Ops | C21: =Data!C22 -> 63348 | D21: =Data!X22 -> 5 | E21: =VLOOKUP(D21, 'Pay Structure'!$A$1:$D$12, 3, FALSE) -> 59831.313 | F21: =C21/E21 -> 1.0587767 | H21: =VLOOKUP(D21, 'Pay Structure'!$A$1:$G$12, 7, FALSE) -> 0.35 | I21: 0
A22: =Data!A23 -> Peer Review Administrator, Audit | B22: =Data!B23 -> Quality Assurance | C22: =Data!C23 -> 56000 | D22: =Data!X23 -> 5 | E22: =VLOOKUP(D22, 'Pay Structure'!$A$1:$D$12, 3, FALSE) -> 59831.313 | F22: =C22/E22 -> 0.93596476 | H22: =VLOOKUP(D22, 'Pay Structure'!$A$1:$G$12, 7, FALSE) -> 0.35 | I22: 0
A23: =Data!A24 -> Peer Review Administrator, Audit | B23: =Data!B24 -> Quality Assurance | C23: =Data!C24 -> 54390 | D23: =Data!X24 -> 5 | E23: =VLOOKUP(D23, 'Pay Structure'!$A$1:$D$12, 3, FALSE) -> 59831.313 | F23: =C23/E23 -> 0.90905577 | H23: =VLOOKUP(D23, 'Pay Structure'!$A$1:$G$12, 7, FALSE) -> 0.35 | I23: 0
A24: =Data!A25 -> Peer Review Administrator, Tax | B24: =Data!B25 -> Quality Assurance | C24: =Data!C25 -> 58700 | D24: =Data!X25 -> 5 | E24: =VLOOKUP(D24, 'Pay Structure'!$A$1:$D$12, 3, FALSE) -> 59831.313 | F24: =C24/E24 -> 0.98109163 | G24: =AVERAGE(F16:F24) -> 0.94444972 | H24: =VLOOKUP(D24, 'Pay Structure'!$A$1:$G$12, 7, FALSE) -> 0.35 | I24: 0
A25: =Data!A26 -> Information Officer | B25: =Data!B26 -> Marketing | C25: =Data!C26 -> 55233 | D25: =Data!X26 -> 6 | E25: =VLOOKUP(D25, 'Pay Structure'!$A$1:$D$12, 3, FALSE) -> 66412.757 | F25: =C25/E25 -> 0.83166251 | H25: =VLOOKUP(D25, 'Pay Structure'!$A$1:$G$12, 7, FALSE) -> 0.35 | I25: 0
A26: =Data!A27 -> Web Developer | B26: =Data!B27 -> IT | C26: =Data!C27 -> 59000 | D26: =Data!X27 -> 6 | E26: =VLOOKUP(D26, 'Pay Structure'!$A$1:$D$12, 3, FALSE) -> 66412.757 | F26: =C26/E26 -> 0.88838354 | H26: =VLOOKUP(D26, 'Pay Structure'!$A$1:$G$12, 7, FALSE) -> 0.35 | I26: 0
A27: =Data!A28 -> Communications Specialist | B27: =Data!B28 -> Marketing | C27: =Data!C28 -> 67040 | D27: =Data!X28 -> 6 | E27: =VLOOKUP(D27, 'Pay Structure'!$A$1:$D$12, 3, FALSE) -> 66412.757 | F27: =C27/E27 -> 1.0094446 | H27: =VLOOKUP(D27, 'Pay Structure'!$A$1:$G$12, 7, FALSE) -> 0.35 | I27: 0
A28: =Data!A29 -> Senior Accountant | B28: =Data!B29 -> Ops | C28: =Data!C29 -> 51082 | D28: =Data!X29 -> 6 | E28: =VLOOKUP(D28, 'Pay Structure'!$A$1:$D$12, 3, FALSE) -> 66412.757 | F28: =C28/E28 -> 0.76915946 | G28: =AVERAGE(F25:F28) -> 0.87466253 | H28: =VLOOKUP(D28, 'Pay Structure'!$A$1:$G$12, 7, FALSE) -> 0.35 | I28: 0
A29: =Data!A30 -> Coordinator, Audit and Assurance | B29: =Data!B30 -> Quality Assurance | C29: =Data!C30 -> 64755 | D29: =Data!X30 -> 7 | E29: =VLOOKUP(D29, 'Pay Structure'!$A$1:$D$12, 3, FALSE) -> 68405.14 | F29: =C29/E29 -> 0.94663939 | H29: =VLOOKUP(D29, 'Pay Structure'!$A$1:$G$12, 7, FALSE) -> 0.35 | I29: 0
A30: =Data!A31 -> Marketing Coordinator | B30: =Data!B31 -> Marketing | C30: =Data!C31 -> 47375 | D30: =Data!X31 -> 7 | E30: =VLOOKUP(D30, 'Pay Structure'!$A$1:$D$12, 3, FALSE) -> 68405.14 | F30: =C30/E30 -> 0.69256492 | G30: =AVERAGE(F29:F30) -> 0.81960216 | H30: =VLOOKUP(D30, 'Pay Structure'!$A$1:$G$12, 7, FALSE) -> 0.35 | I30: 0
A31: =Data!A32 -> Coordinator, Professional Programs | B31: =Data!B32 -> Continuing Education | C31: =Data!C32 -> 53042 | D31: =Data!X32 -> 8 | E31: =VLOOKUP(D31, 'Pay Structure'!$A$1:$D$12, 3, FALSE) -> 75929.705 | F31: =C31/E31 -> 0.69856718 | H31: =VLOOKUP(D31, 'Pay Structure'!$A$1:$G$12, 7, FALSE) -> 0.35 | I31: 0
A32: =Data!A33 -> Manager Conferences and Event Planning | B32: =Data!B33 -> Continuing Education | C32: =Data!C33 -> 72180 | D32: =Data!X33 -> 8 | E32: =VLOOKUP(D32, 'Pay Structure'!$A$1:$D$12, 3, FALSE) -> 75929.705 | F32: =C32/E32 -> 0.9506161 | H32: =VLOOKUP(D32, 'Pay Structure'!$A$1:$G$12, 7, FALSE) -> 0.35 | I32: 0
A33: =Data!A34 -> Manager, Workforce Recruitment | B33: =Data!B34 -> Marketing | C33: =Data!C34 -> 83828 | D33: =Data!X34 -> 8 | E33: =VLOOKUP(D33, 'Pay Structure'!$A$1:$D$12, 3, FALSE) -> 75929.705 | F33: =C33/E33 -> 1.1040211 | H33: =VLOOKUP(D33, 'Pay Structure'!$A$1:$G$12, 7, FALSE) -> 0.35 | I33: 0
A34: =Data!A35 -> Manager, Education Outreach | B34: =Data!B35 -> Marketing | C34: =Data!C35 -> 81247 | D34: =Data!X35 -> 8 | E34: =VLOOKUP(D34, 'Pay Structure'!$A$1:$D$12, 3, FALSE) -> 75929.705 | F34: =C34/E34 -> 1.0700292 | H34: =VLOOKUP(D34, 'Pay Structure'!$A$1:$G$12, 7, FALSE) -> 0.35 | I34: 0
A35: =Data!A36 -> Manager Finance and Administration | B35: =Data!B36 -> Ops | C35: =Data!C36 -> 69733 | D35: =Data!X36 -> 8 | E35: =VLOOKUP(D35, 'Pay Structure'!$A$1:$D$12, 3, FALSE) -> 75929.705 | F35: =C35/E35 -> 0.91838892 | G35: =AVERAGE(F31:F35) -> 0.94832451 | H35: =VLOOKUP(D35, 'Pay Structure'!$A$1:$G$12, 7, FALSE) -> 0.35 | I35: 0
A36: =Data!A37 -> Manager, Executive Office | B36: =Data!B37 -> Exec | C36: =Data!C37 -> 71707 | D36: =Data!X37 -> 9 | E36: =VLOOKUP(D36, 'Pay Structure'!$A$1:$D$12, 3, FALSE) -> 87319.161 | F36: =C36/E36 -> 0.82120579 | H36: =VLOOKUP(D36, 'Pay Structure'!$A$1:$G$12, 7, FALSE) -> 0.35 | I36: 0
A37: =Data!A38 -> Manager, Audit and Assurance | B37: =Data!B38 -> Quality Assurance | C37: =Data!C38 -> 84980 | D37: =Data!X38 -> 9 | E37: =VLOOKUP(D37, 'Pay Structure'!$A$1:$D$12, 3, FALSE) -> 87319.161 | F37: =C37/E37 -> 0.97321137 | H37: =VLOOKUP(D37, 'Pay Structure'!$A$1:$G$12, 7, FALSE) -> 0.35 | I37: 0
A38: =Data!A39 -> Manager, Tax Quality | B38: =Data!B39 -> Quality Assurance | C38: =Data!C39 -> 70000 | D38: =Data!X39 -> 9 | E38: =VLOOKUP(D38, 'Pay Structure'!$A$1:$D$12, 3, FALSE) -> 87319.161 | F38: =C38/E38 -> 0.80165681 | H38: =VLOOKUP(D38, 'Pay Structure'!$A$1:$G$12, 7, FALSE) -> 0.35 | I38: 0
A39: =Data!A40 -> Manager, Member Services Centre | B39: =Data!B40 -> Ops | C39: =Data!C40 -> 95151 | D39: =Data!X40 -> 9 | E39: =VLOOKUP(D39, 'Pay Structure'!$A$1:$D$12, 3, FALSE) -> 87319.161 | F39: =C39/E39 -> 1.0896921 | H39: =VLOOKUP(D39, 'Pay Structure'!$A$1:$G$12, 7, FALSE) -> 0.35 | I39: 0
A40: =Data!A41 -> Director, IT | B40: =Data!B41 -> IT | C40: =Data!C41 -> 101981 | D40: =Data!X41 -> 9 | E40: =VLOOKUP(D40, 'Pay Structure'!$A$1:$D$12, 3, FALSE) -> 87319.161 | F40: =C40/E40 -> 1.1679109 | H40: =VLOOKUP(D40, 'Pay Structure'!$A$1:$G$12, 7, FALSE) -> 0.35 | I40: 0
A41: =Data!A42 -> Director, Continuing Education | B41: =Data!B42 -> Continuing Education | C41: =Data!C42 -> 83860 | D41: =Data!X42 -> 9 | E41: =VLOOKUP(D41, 'Pay Structure'!$A$1:$D$12, 3, FALSE) -> 87319.161 | F41: =C41/E41 -> 0.96038486 | G41: =AVERAGE(F36:F41) -> 0.96901031 | H41: =VLOOKUP(D41, 'Pay Structure'!$A$1:$G$12, 7, FALSE) -> 0.35 | I41: 0
A42: =Data!A43 -> Director, Quality Assurance | B42: =Data!B43 -> Quality Assurance | C42: =Data!C43 -> 114302 | D42: =Data!X43 -> 10 | E42: =VLOOKUP(D42, 'Pay Structure'!$A$1:$D$12, 3, FALSE) -> 100417.03 | F42: =C42/E42 -> 1.138273 | H42: =VLOOKUP(D42, 'Pay Structure'!$A$1:$G$12, 7, FALSE) -> 0.35 | I42: 0
A43: =Data!A44 -> Director, Marketing and Communications | B43: =Data!B44 -> Marketing | C43: =Data!C44 -> 118571 | D43: =Data!X44 -> 10 | E43: =VLOOKUP(D43, 'Pay Structure'!$A$1:$D$12, 3, FALSE) -> 100417.03 | F43: =C43/E43 -> 1.1807857 | H43: =VLOOKUP(D43, 'Pay Structure'!$A$1:$G$12, 7, FALSE) -> 0.35 | I43: 0
A44: =Data!A45 -> Director, Operations | B44: =Data!B45 -> Ops | C44: =Data!C45 -> 126947 | D44: =Data!X45 -> 10 | E44: =VLOOKUP(D44, 'Pay Structure'!$A$1:$D$12, 3, FALSE) -> 100417.03 | F44: =C44/E44 -> 1.2641979 | G44: =AVERAGE(F42:F44) -> 1.1944189 | H44: =VLOOKUP(D44, 'Pay Structure'!$A$1:$G$12, 7, FALSE) -> 0.35 | I44: 0
A45: =Data!A46 -> Executive Director | B45: =Data!B46 -> Exec | C45: =Data!C46 -> 171619 | D45: =Data!X46 -> 11 | E45: =VLOOKUP(D45, 'Pay Structure'!$A$1:$D$12, 3, FALSE) -> 115479.59 | F45: =C45/E45 -> 1.4861414 | G45: =F45 -> 1.4861414 | H45: =VLOOKUP(D45, 'Pay Structure'!$A$1:$G$12, 7, FALSE) -> 0.5 | I45: 0

Sheet Benchmarking Calculations
A2: Survey | B2: Title | C2: Base Salary | D2: Market Segment | E2: N Org | F2: Position Title | G2: 0.5 | H2: Mean | I2: Actual Compa Ratio 50%
B3: Secretary, Director of Continuing Education | C3: =Data!C11/1000 -> 43.898
A4: Mercer | D4: Not For Profit & Public Sector | E4: 38 | F4: Administrative Assistant - Senior | G4: 45.4
D5: Greater Toronto | E5: 143 | F5: Administrative Assistant - Senior | G5: 48
D6: Revenues 50 to 100 million | E6: 11 | F6: Administrative Assistant - Senior | G6: 50.2
A7: Watson Wyatt | D7: Not-for-Profit | E7: 19 | F7: Administrative Assistant - Senior | G7: 45.3
D8: Greater Toronto | E8: 79 | F8: Administrative Assistant - Senior | G8: 49
A10: Benchmark | C10: =(E4/E10)*G4+(E5/E10)*G5+(E6/E10)*G6+(E7/E10)*G7+(E8/E10)*G8 -> 47.838276 | D10: Total N Org: | E10: =SUM(E4:E8) -> 290 | I10: =C3/C10 -> 0.91763341
A12: Survey | B12: Title | C12: Base Salary | D12: Market Segment | E12: N Org | F12: Position Title | G12: 0.5 | H12: Mean | I12: Actual Compa Ratio 50%
B13: Seminar Coodinator | C13: =AVERAGE(Data!C9:C10)/1000 -> 37.9415
A14: Mercer | D14: Not For Profit & Public Sector | E14: 10 | F14: Events Planner | G14: 49.9
D15: Greater Toronto | E15: 25 | F15: Events Planner | G15: 50.4
A17: Benchmark | C17: =(E14/E17)*G14+(E15/E17)*G15 -> 50.257143 | D17: Total N Org: | E17: =SUM(E14:E16) -> 35 | I17: =C13/C17 -> 0.75494741
A19: Survey | B19: Title | C19: Base Salary | D19: Market Segment | E19: N Org | F19: Position Title | G19: 0.5 | H19: Mean | I19: Actual Compa Ratio 50%
B20: Meetings & District Programs Coordinator | C20: =Data!C7/1000 -> 42.908
A21: Mercer | D21: Not For Profit & Public Sector | E21: 10 | F21: Events Planner | G21: 49.9
D22: Greater Toronto | E22: 25 | F22: Events Planner | G22: 50.4
A24: Benchmark | C24: =(E21/E24)*G21+(E22/E24)*G22 -> 50.257143 | D24: Total N Org: | E24: =SUM(E21:E23) -> 35 | I24: =C20/C24 -> 0.85376919
A26: Survey | B26: Title | C26: Base Salary | D26: Market Segment | E26: N Org | F26: Position Title | G26: 0.5 | H26: Mean | I26: Actual Compa Ratio 50%
B27: Manager Conferences and Event Planning | C27: =Data!C33/1000 -> 72.18
A28: Mercer | D28: Not For Profit & Public Sector | E28: 4 | F28: Meeting Planner and Special Events Manager | G28: 64.3
D29: Greater Toronto | E29: 17 | F29: Meeting Planner and Special Events Manager | G29: 70.9
A31: Benchmark | C31: =(E28/E31)*G28+(E29/E31)*G29 -> 69.642857 | D31: Total N Org: | E31: =SUM(E28:E29) -> 21 | I31: =C27/C31 -> 1.0364308
A33: Survey | B33: Title | C33: Base Salary | D33: Market Segment | E33: N Org | F33: Position Title | G33: 0.5 | H33: Mean | I33: Actual Compa Ratio 50%
B34: Administrative Assistant, Executive Office | C34: =Data!C13/1000 -> 37.258
A35: Mercer | D35: Not For Profit & Public Sector | E35: 42 | F35: Executive Administrative Assistant | G35: 53.5
D36: Greater Toronto | E36: 172 | F36: Executive Administrative Assistant | G36: 55.5
D37: Revenues 50 to 100 million | E37: 17 | F37: Executive Administrative Assistant | G37: 53.5
A38: Watson Wyatt | D38: Not-for-Profit | E38: 20 | F38: Administrative Assistant - Executive | G38: 55.2
D39: Greater Toronto | E39: 81 | F39: Administrative Assistant - Executive | G39: 57
A41: Benchmark | C41: =(E35/E41)*G35+(E36/E41)*G36+(E37/E41)*G37+(E38/E41)*G38+(E39/E41)*G39 -> 55.49247 | D41: Total N Org: | E41: =SUM(E35:E39) -> 332 | I41: =C34/C41 -> 0.67140641
A43: Survey | B43: Title | C43: Base Salary | D43: Market Segment | E43: N Org | F43: Position Title | G43: 0.5 | H43: Mean | I43: Actual Compa Ratio 50%
B44: Director, Information Systems | C44: =Data!C41/1000 -> 101.981
A45: Mercer | D45: Not For Profit & Public Sector | E45: 25 | F45: Chief Information officer | G45: 149.4
D46: Revenues 50 to 100 million | E46: 4 | F46: Chief Information officer | G46: 128.6
A47: Towers Perrin | D47: Under $100 million | E47: 4 | F47: Chief Information officer | G47: 175.8
A49: Benchmark | C49: =(E45/E49)*G45+(E46/E49)*G46+(E47/E49)*G47 -> 150.07879 | D49: Total N Org: | E49: =SUM(E45:E47) -> 33 | I49: =C44/C49 -> 0.67951642
A51: Survey | B51: Title | C51: Base Salary | D51: Market Segment | E51: N Org | F51: Position Title | G51: 0.5 | H51: Mean | I51: Actual Compa Ratio 50%
B52: Executive Director | C52: =Data!C46/1000 -> 171.619
A53: Mercer | D53: Not For Profit & Public Sector | E53: 32 | F53: CEO | G53: 280.8
D54: Revenues 50 to 100 million | E54: 9 | F54: CEO | G54: 190
A55: Towers Perrin | D55: Under $100 million | E55: 21 | F55: CEO | G55: 275
A57: Benchmark | C57: =(E53/E57)*G53+(E54/E57)*G54+(E55/E57)*G55 -> 265.65484 | D57: Total N Org: | E57: =SUM(E53:E55) -> 62 | I57: =C52/C57 -> 0.64602249
A59: Survey | B59: Title | C59: Base Salary | D59: Market Segment | E59: N Org | F59: Position Title | G59: 0.5 | H59: Mean | I59: Actual Compa Ratio 50%
B60: Director, Marketing and Communications | C60: =Data!C44/1000 -> 118.571
A61: Mercer | D61: Revenues 50 to 100 million | E61: 4 | F61: Marketing Executive | G61: 154.9
A62: Towers Perrin | D62: Under $1 billion | E62: 12 | F62: Top Sales and Marketing Executive | G62: 185.8
A64: Benchmark | C64: =(E61/E64)*G61+(E62/E64)*G62 -> 178.075 | D64: Total N Org: | E64: =SUM(E61:E62) -> 16 | I64: =C60/C64 -> 0.66584866
A66: Survey | B66: Title | C66: Base Salary | D66: Market Segment | E66: N Org | F66: Position Title | G66: 0.5 | H66: Mean | I66: Actual Compa Ratio 50%
B67: Marketing Coordinator | C67: =Data!C31/1000 -> 47.375
A68: Mercer | D68: Not For Profit & Public Sector | E68: 5 | F68: Marketing Co-ordinator | G68: 48.7
D69: Greater Toronto | E69: 61 | F69: Marketing Co-ordinator | G69: 48.2
D70: Revenues 50 to 100 million | E70: 9 | F70: Marketing Co-ordinator | G70: 45
A72: Benchmark | C72: =(E68/E72)*G68+(E69/E72)*G69+(E70/E72)*G70 -> 47.849333 | D72: Total N Org: | E72: =SUM(E68:E70) -> 75 | I72: =C67/C72 -> 0.99008694
A74: Survey | B74: Title | C74: Base Salary | D74: Market Segment | E74: N Org | F74: Position Title | G74: 0.5 | H74: Mean | I74: Actual Compa Ratio 50%
B75: Accountant | C75: =Data!C17/1000 -> 41.53
A76: Mercer | D76: Not For Profit & Public Sector | E76: 16 | F76: Accountant - Intermediate | G76: 53.5
D77: Greater Toronto | E77: 104 | F77: Accountant - Intermediate | G77: 55.5
D78: Revenues 50 to 100 million | E78: 16 | F78: Accountant - Intermediate | G78: 51.3
A79: Watson Wyatt | D79: Not-for-Profit | E79: 11 | F79: Accountant - Intermediate | G79: 52.7
D80: Greater Toronto | E80: 44 | F80: Accountant - Intermediate | G80: 48.6
A82: Benchmark | C82: =(E76/E82)*G76+(E77/E82)*G77+(E78/E82)*G78+(E79/E82)*G79+(E80/E82)*G80 -> 53.229843 | D82: Total N Org: | E82: =SUM(E76:E80) -> 191 | I82: =C75/C82 -> 0.78020144
A84: Survey | B84: Title | C84: Base Salary | D84: Market Segment | E84: N Org | F84: Position Title | G84: 0.5 | H84: Mean | I84: Actual Compa Ratio 50%
B85: Administrative Clerk (operations) | C85: =AVERAGE(Data!C5,Data!C6)/1000 -> 34.0605
A86: Mercer | D86: Not For Profit & Public Sector | E86: 25 | F86: Clerk - Intermediate | G86: 42.5
D87: Greater Toronto | E87: 77 | F87: Clerk - Intermediate | G87: 38.8
D88: Revenues 50 to 100 million | E88: 6 | F88: Clerk - Intermediate | G88: 30.6
A89: Watson Wyatt | D89: Not-for-Profit | E89: 8 | F89: Clerical - Intermediate | G89: 37.3
D90: Greater Toronto | E90: 41 | F90: Clerical - Intermediate | G90: 36.4
A92: Benchmark | C92: =(E86/E92)*G86+(E87/E92)*G87+(E88/E92)*G88+(E89/E92)*G89+(E90/E92)*G90 -> 38.372611 | D92: Total N Org: | E92: =SUM(E86:E90) -> 157 | I92: =C85/C92 -> 0.88762528
A94: Survey | B94: Title | C94: Base Salary | D94: Market Segment | E94: N Org | F94: Position Title | G94: 0.5 | H94: Mean | I94: Actual Compa Ratio 50%
B95: Administrative Clerk/Mailroom (operations) | C95: =Data!C16/1000 -> 40.429
A96: Mercer | D96: Not For Profit & Public Sector | E96: 25 | F96: Clerk - Intermediate | G96: 42.5
D97: Greater Toronto | E97: 77 | F97: Clerk - Intermediate | G97: 38.8
D98: Revenues 50 to 100 million | E98: 6 | F98: Clerk - Intermediate | G98: 30.6
A100: Benchmark | C100: =(E96/E100)*G96+(E97/E100)*G97+(E98/E100)*G98 -> 39.200926 | D100: Total N Org: | E100: =SUM(E96:E98) -> 108 | I100: =C95/C100 -> 1.0313277
A102: Survey | B102: Title | C102: Base Salary | D102: Market Segment | E102: N Org | F102: Position Title | G102: 0.5 | H102: Mean | I102: Actual Compa Ratio 50%
B103: Junior Accountant | C103: =Data!C14/1000 -> 32.81
A104: Mercer | D104: Not For Profit & Public Sector | E104: 9 | F104: Accountant - Associate | G104: 45.4
D105: Greater Toronto | E105: 44 | F105: Accountant - Associate | G105: 45.9
D106: Revenues 50 to 100 million | E106: 5 | F106: Accountant - Associate | G106: 43.5
A107: Watson Wyatt | D107: Greater Toronto | E107: 18 | F107: Accountant - Entry | G107: 39.3
A109: Benchmark | C109: =(E104/E109)*G104+(E105/E109)*G105+(E106/E109)*G106+(E107/E109)*G107 -> 44.119737 | D109: Total N Org: | E109: =SUM(E104:E107) -> 76 | I109: =C103/C109 -> 0.74365811
A111: Survey | B111: Title | C111: Base Salary | D111: Market Segment | E111: N Org | F111: Position Title | G111: 0.5 | H111: Mean | I111: Actual Compa Ratio 50%
B112: Manager, Finance & Admin | C112: =Data!C36/1000 -> 69.733
A113: Mercer | D113: Not For Profit & Public Sector | E113: 11 | F113: Finance Manager | G113: 72.8
D114: Greater Toronto | E114: 52 | F114: Finance Manager | G114: 87
D115: Revenues 50 to 100 million | E115: 6 | F115: Finance Manager | G115: 92.5
D116: Not For Profit & Public Sector | E116: 21 | F116: Accounting Manager | G116: 79.6
D117: Greater Toronto | E117: 119 | F117: Accounting Manager | G117: 86.2
D118: Revenues 50 to 100 million | E118: 11 | F118: Accounting Manager | G118: 82.5
A119: Watson Wyatt | D119: Not-for-Profit | E119: 10 | F119: General Accounting Manager | G119: 78.3
D120: Greater Toronto | E120: 57 | F120: General Accounting Manager | G120: 86.7
A122: Benchmark | C122: =(E113/E122)*G113+(E114/E122)*G114+(E115/E122)*G115+(E116/E122)*G116+(E117/E122)*G117+(E118/E122)*G118+(E119/E122)*G119+(E120/E122)*G120 -> 85.162369 | D122: Total N Org: | E122: =SUM(E113:E120) -> 287 | I122: =C112/C122 -> 0.81882409
A124: Survey | B124: Title | C124: Base Salary | D124: Market Segment | E124: N Org | F124: Position Title | G124: 0.5 | H124: Mean | I124: Actual Compa Ratio 50%
B125: Receptionist | C125: =Data!C4/1000 -> 44.526
A126: Mercer | D126: Not For Profit & Public Sector | E126: 32 | F126: Receptionist | G126: 37.1
D127: Greater Toronto | E127: 126 | F127: Receptionist | G127: 35.2
D128: Revenues 50 to 100 million | E128: 19 | F128: Receptionist | G128: 33.3
A129: Watson Wyatt | D129: Not-for-Profit | E129: 16 | F129: Receptionist | G129: 34.1
...

Sheet Internal vs External compa
A1: Position Title | B1: Department | C1: Internal Compa-Ratio | D1: External Compa-Ratio | E1: % Difference
A2: =Data!A3 -> Administrative Clerk | B2: =Data!B3 -> Quality Assurance | C2: ='Internal Compa-ratios'!F2 -> 0.94494481 | D2: ='Benchmarking Calculations'!I162 -> 0.94494481 | E2: =C2-D2 -> 0
A3: =Data!A4 -> Receptionist | B3: =Data!B4 -> Ops | C3: ='Internal Compa-ratios'!F3 -> 1.0360347 | D3: ='Benchmarking Calculations'!I132 -> 1.2617923 | E3: =C3-D3 -> -0.22575757
A4: =Data!A5 -> Administrative Clerk | B4: =Data!B5 -> Ops | C4: ='Internal Compa-ratios'!F4 -> 0.84028031 | D4: ='Benchmarking Calculations'!I92 -> 0.88762528 | E4: =C4-D4 -> -0.047344966
A5: =Data!A6 -> Administrative Clerk | B5: =Data!B6 -> Ops | C5: ='Internal Compa-ratios'!F5 -> 0.74476483 | D5: ='Benchmarking Calculations'!I92 -> 0.88762528 | E5: =C5-D5 -> -0.14286045
A6: =Data!A7 -> Meetings and District Programs Coordinator | B6: =Data!B7 -> Continuing Education | C6: ='Internal Compa-ratios'!F6 -> 0.89141691 | D6: ='Benchmarking Calculations'!I24 -> 0.85376919 | E6: =C6-D6 -> 0.037647727
A7: =Data!A8 -> Circulation Technician & Receptionist | B7: =Data!B8 -> Ops | C7: ='Internal Compa-ratios'!F7 -> 0.96564626
A8: =Data!A9 -> Seminar Coordinator | B8: =Data!B9 -> Continuing Education | C8: ='Internal Compa-ratios'!F8 -> 0.80011046 | D8: ='Benchmarking Calculations'!I17 -> 0.75494741 | E8: =C8-D8 -> 0.045163047
A9: =Data!A10 -> Seminar Coordinator | B9: =Data!B10 -> Continuing Education | C9: ='Internal Compa-ratios'!F9 -> 0.77636455 | D9: ='Benchmarking Calculations'!I17 -> 0.75494741 | E9: =C9-D9 -> 0.021417136
A10: =Data!A11 -> Secretary (Director Continuing Education) | B10: =Data!B11 -> Continuing Education | C10: ='Internal Compa-ratios'!F10 -> 0.91198424 | D10: ='Benchmarking Calculations'!I10 -> 0.91763341 | E10: =C10-D10 -> -0.0056491674
A11: =Data!A12 -> Junior Systems Administrator | B11: =Data!B12 -> IT | C11: ='Internal Compa-ratios'!F11 -> 0.78378692
A12: =Data!A13 -> Administrative Assistant, Exec Office | B12: =Data!B13 -> Exec | C12: ='Internal Compa-ratios'!F12 -> 0.70367067 | D12: ='Benchmarking Calculations'!I41 -> 0.67140641 | E12: =C12-D12 -> 0.032264263
A13: =Data!A14 -> Junior Accountant | B13: =Data!B14 -> Ops | C13: ='Internal Compa-ratios'!F13 -> 0.61966383 | D13: ='Benchmarking Calculations'!I109 -> 0.74365811 | E13: =C13-D13 -> -0.12399428
A14: =Data!A15 -> Business Research Coordinator | B14: =Data!B15 -> Ops | C14: ='Internal Compa-ratios'!F14 -> 1.095413
A15: =Data!A16 -> Administrative Clerk/mailroom clerk | B15: =Data!B16 -> Ops | C15: ='Internal Compa-ratios'!F15 -> 0.76355955 | D15: ='Benchmarking Calculations'!I100 -> 1.0313277 | E15: =C15-D15 -> -0.26776813
A16: =Data!A17 -> Accountant | B16: =Data!B17 -> Ops | C16: ='Internal Compa-ratios'!F16 -> 0.69411815 | D16: ='Benchmarking Calculations'!I82 -> 0.78020144 | E16: =C16-D16 -> -0.086083288
A17: =Data!A18 -> Programmer | B17: =Data!B18 -> IT | C17: ='Internal Compa-ratios'!F17 -> 1.2917818
A18: =Data!A19 -> Career Consultant | B18: =Data!B19 -> Ops | C18: ='Internal Compa-ratios'!F18 -> 1.1482282
A19: =Data!A20 -> Associate Coordinator, Professional Programs | B19: =Data!B20 -> Continuing Education | C19: ='Internal Compa-ratios'!F19 -> 0.65357082
A20: =Data!A21 -> Secretary (Director Operations) | B20: =Data!B21 -> Ops | C20: ='Internal Compa-ratios'!F20 -> 0.8274597 | D20: ='Benchmarking Calculations'!I142 -> 1.0349035 | E20: =C20-D20 -> -0.20744382
A21: =Data!A22 -> Business Analyst | B21: =Data!B22 -> Ops | C21: ='Internal Compa-ratios'!F21 -> 1.0587767
A22: =Data!A23 -> Peer Review Administrator, Audit | B22: =Data!B23 -> Quality Assurance | C22: ='Internal Compa-ratios'!F22 -> 0.93596476
A23: =Data!A24 -> Peer Review Administrator, Audit | B23: =Data!B24 -> Quality Assurance | C23: ='Internal Compa-ratios'!F23 -> 0.90905577
A24: =Data!A25 -> Peer Review Administrator, Tax | B24: =Data!B25 -> Quality Assurance | C24: ='Internal Compa-ratios'!F24 -> 0.98109163
A25: =Data!A26 -> Information Officer | B25: =Data!B26 -> Marketing | C25: ='Internal Compa-ratios'!F25 -> 0.83166251
A26: =Data!A27 -> Web Developer | B26: =Data!B27 -> IT | C26: ='Internal Compa-ratios'!F26 -> 0.88838354
A27: =Data!A28 -> Communications Specialist | B27: =Data!B28 -> Marketing | C27: ='Internal Compa-ratios'!F27 -> 1.0094446 | D27: ='Benchmarking Calculations'!I182 -> 1.15832 | E27: =C27-D27 -> -0.14887543
A28: =Data!A29 -> Senior Accountant | B28: =Data!B29 -> Ops | C28: ='Internal Compa-ratios'!F28 -> 0.76915946 | D28: ='Benchmarking Calculations'!I152 -> 0.74665312 | E28: =C28-D28 -> 0.022506337
A29: =Data!A30 -> Coordinator, Audit and Assurance | B29: =Data!B30 -> Quality Assurance | C29: ='Internal Compa-ratios'!F29 -> 0.94663939 | D29: ='Benchmarking Calculations'!I169 -> 0.91829941 | E29: =C29-D29 -> 0.028339981
A30: =Data!A31 -> Marketing Coordinator | B30: =Data!B31 -> Marketing | C30: ='Internal Compa-ratios'!F30 -> 0.69256492 | D30: ='Benchmarking Calculations'!I72 -> 0.99008694 | E30: =C30-D30 -> -0.29752202
A31: =Data!A32 -> Coordinator, Professional Programs | B31: =Data!B32 -> Continuing Education | C31: ='Internal Compa-ratios'!F31 -> 0.69856718
A32: =Data!A33 -> Manager Conferences and Event Planning | B32: =Data!B33 -> Continuing Education | C32: ='Internal Compa-ratios'!F32 -> 0.9506161 | D32: ='Benchmarking Calculations'!I31 -> 1.0364308 | E32: =C32-D32 -> -0.08581467
A33: =Data!A34 -> Manager, Workforce Recruitment | B33: =Data!B34 -> Marketing | C33: ='Internal Compa-ratios'!F33 -> 1.1040211
A34: =Data!A35 -> Manager, Education Outreach | B34: =Data!B35 -> Marketing | C34: ='Internal Compa-ratios'!F34 -> 1.0700292
A35: =Data!A36 -> Manager Finance and Administration | B35: =Data!B36 -> Ops | C35: ='Internal Compa-ratios'!F35 -> 0.91838892 | D35: ='Benchmarking Calculations'!I122 -> 0.81882409 | E35: =C35-D35 -> 0.099564828
A36: =Data!A37 -> Manager, Executive Office | B36: =Data!B37 -> Exec | C36: ='Internal Compa-ratios'!F36 -> 0.82120579
A37: =Data!A38 -> Manager, Audit and Assurance | B37: =Data!B38 -> Quality Assurance | C37: ='Internal Compa-ratios'!F37 -> 0.97321137
A38: =Data!A39 -> Manager, Tax Quality | B38: =Data!B39 -> Quality Assurance | C38: ='Internal Compa-ratios'!F38 -> 0.80165681
A39: =Data!A40 -> Manager, Member Services Centre | B39: =Data!B40 -> Ops | C39: ='Internal Compa-ratios'!F39 -> 1.0896921
A40: =Data!A41 -> Director, IT | B40: =Data!B41 -> IT | C40: ='Internal Compa-ratios'!F40 -> 1.1679109 | D40: ='Benchmarking Calculations'!I49 -> 0.67951642 | E40: =C40-D40 -> 0.48839449
A41: =Data!A42 -> Director, Continuing Education | B41: =Data!B42 -> Continuing Education | C41: ='Internal Compa-ratios'!F41 -> 0.96038486
A42: =Data!A43 -> Director, Quality Assurance | B42: =Data!B43 -> Quality Assurance | C42: ='Internal Compa-ratios'!F42 -> 1.138273
A43: =Data!A44 -> Director, Marketing and Communications | B43: =Data!B44 -> Marketing | C43: ='Internal Compa-ratios'!F43 -> 1.1807857 | D43: ='Benchmarking Calculations'!I64 -> 0.66584866 | E43: =C43-D43 -> 0.51493705
A44: =Data!A45 -> Director, Operations | B44: =Data!B45 -> Ops | C44: ='Internal Compa-ratios'!F44 -> 1.2641979
A45: =Data!A46 -> Executive Director | B45: =Data!B46 -> Exec | C45: ='Internal Compa-ratios'!F45 -> 1.4861414 | D45: ='Benchmarking Calculations'!I57 -> 0.64602249 | E45: =C45-D45 -> 0.84011891

Sheet Budget
A1: Grade | B1: Minimum | C1: Midpoint | D1: Maximum | E1: Count | F1: Payroll at mid | G1: Payroll at max | H1: Midpoint Progression | I1: Midpoint Width
A2: 1 | B2: ='Pay Structure'!B2 -> 24942.197 | C2: ='Pay Structure'!C2 -> 38372.611 | D2: ='Pay Structure'!D2 -> 51803.025 | E2: =COUNTIF(Data!X:X, A2) -> 1 | F2: =C2*E2 -> 38372.611 | G2: =D2*E2 -> 51803.025 | I2: ='Pay Structure'!G2 -> 0.35
A3: 2 | B3: ='Pay Structure'!B3 -> 27935.261 | C3: ='Pay Structure'!C3 -> 42977.325 | D3: ='Pay Structure'!D3 -> 58019.389 | E3: =COUNTIF(Data!X:X, A3) -> 3 | F3: =C3*E3 -> 128931.97 | G3: =D3*E3 -> 174058.17 | H3: ='Pay Structure'!F3 -> 0.12 | I3: ='Pay Structure'!G3 -> 0.35
A4: 3 | B4: ='Pay Structure'!B4 -> 31287.492 | C4: ='Pay Structure'!C4 -> 48134.604 | D4: ='Pay Structure'!D4 -> 64981.715 | E4: =COUNTIF(Data!X:X, A4) -> 5 | F4: =C4*E4 -> 240673.02 | G4: =D4*E4 -> 324908.58 | H4: ='Pay Structure'!F4 -> 0.12 | I4: ='Pay Structure'!G4 -> 0.35
A5: 4 | B5: ='Pay Structure'!B5 -> 34416.242 | C5: ='Pay Structure'!C5 -> 52948.064 | D5: ='Pay Structure'!D5 -> 71479.887 | E5: =COUNTIF(Data!X:X, A5) -> 5 | F5: =C5*E5 -> 264740.32 | G5: =D5*E5 -> 357399.43 | H5: ='Pay Structure'!F5 -> 0.1 | I5: ='Pay Structure'!G5 -> 0.35
A6: 5 | B6: ='Pay Structure'!B6 -> 38890.353 | C6: ='Pay Structure'!C6 -> 59831.313 | D6: ='Pay Structure'!D6 -> 80772.272 | E6: =COUNTIF(Data!X:X, A6) -> 9 | F6: =C6*E6 -> 538481.81 | G6: =D6*E6 -> 726950.45 | H6: ='Pay Structure'!F6 -> 0.13 | I6: ='Pay Structure'!G6 -> 0.35
A7: 6 | B7: ='Pay Structure'!B7 -> 43168.292 | C7: ='Pay Structure'!C7 -> 66412.757 | D7: ='Pay Structure'!D7 -> 89657.222 | E7: =COUNTIF(Data!X:X, A7) -> 4 | F7: =C7*E7 -> 265651.03 | G7: =D7*E7 -> 358628.89 | H7: ='Pay Structure'!F7 -> 0.11 | I7: ='Pay Structure'!G7 -> 0.35
A8: 7 | B8: ='Pay Structure'!B8 -> 44463.341 | C8: ='Pay Structure'!C8 -> 68405.14 | D8: ='Pay Structure'!D8 -> 92346.939 | E8: =COUNTIF(Data!X:X, A8) -> 2 | F8: =C8*E8 -> 136810.28 | G8: =D8*E8 -> 184693.88 | H8: ='Pay Structure'!F8 -> 0.03 | I8: ='Pay Structure'!G8 -> 0.35
A9: 8 | B9: ='Pay Structure'!B9 -> 49354.308 | C9: ='Pay Structure'!C9 -> 75929.705 | D9: ='Pay Structure'!D9 -> 102505.1 | E9: =COUNTIF(Data!X:X, A9) -> 5 | F9: =C9*E9 -> 379648.52 | G9: =D9*E9 -> 512525.51 | H9: ='Pay Structure'!F9 -> 0.11 | I9: ='Pay Structure'!G9 -> 0.35
A10: 9 | B10: ='Pay Structure'!B10 -> 56757.454 | C10: ='Pay Structure'!C10 -> 87319.161 | D10: ='Pay Structure'!D10 -> 117880.87 | E10: =COUNTIF(Data!X:X, A10) -> 6 | F10: =C10*E10 -> 523914.96 | G10: =D10*E10 -> 707285.2 | H10: ='Pay Structure'!F10 -> 0.15 | I10: ='Pay Structure'!G10 -> 0.35
A11: 10 | B11: ='Pay Structure'!B11 -> 65271.073 | C11: ='Pay Structure'!C11 -> 100417.03 | D11: ='Pay Structure'!D11 -> 135563 | E11: =COUNTIF(Data!X:X, A11) -> 3 | F11: =C11*E11 -> 301251.1 | G11: =D11*E11 -> 406688.99 | H11: ='Pay Structure'!F11 -> 0.15 | I11: ='Pay Structure'!G11 -> 0.35
A12: 11 | B12: ='Pay Structure'!B12 -> 57739.795 | C12: ='Pay Structure'!C12 -> 115479.59 | D12: ='Pay Structure'!D12 -> 173219.39 | E12: =COUNTIF(Data!X:X, A12) -> 1 | F12: =C12*E12 -> 115479.59 | G12: =D12*E12 -> 173219.39 | H12: ='Pay Structure'!F12 -> 0.15 | I12: ='Pay Structure'!G12 -> 0.5
D14: Total: | E14: =SUM(E2:E12) -> 44 | F14: =SUM(F2:F12) -> 2933955.2 | G14: =SUM(G2:G12) -> 3978161.5
F15: Is Less than 4M? | G15: =G14<=4000000 -> TRUE

Sheet Pay Equity
A1: Position Title | B1: Department | C1: Gender | D1: 2007 Salary | E1: Total Points | F1: Grade | G1: Job Class | H1: Dominance | I1: Gender of Class | J1: PE Method | K1: Male Comparator | L1: PE Adjustment | M1: Proposed Min | N1: Final Adjustment | O1: Justification
A2: Administrative Clerk | B2: Quality Assurance | C2: F | D2: 36260 | E2: =VLOOKUP(A2, Data!$A$2:$Z$46, 23, FALSE) -> 255 | F2: =VLOOKUP(A2, Data!$A$2:$Z$46, 24, FALSE) -> 1 | G2: 1 | H2: 100% Female | I2: F | J2: PV | K2: ='PV Regression Results'!$B$17+'PV Regression Results'!$B$18*'Pay Equity'!E2 -> 38903.624 | L2: =IF(K2>D2, K2-D2, 0) -> 2643.6236 | M2: =VLOOKUP(F2, 'Pay Structure'!$A$1:$D$12, 2, FALSE) -> 24942.197 | N2: =IF(K2>M2, L2, M2-D2) -> 2643.6236 | O2: Unique
A3: Receptionist | B3: Ops | C3: F | D3: 44526 | E3: =VLOOKUP(A3, Data!$A$2:$Z$46, 23, FALSE) -> 260 | F3: =VLOOKUP(A3, Data!$A$2:$Z$46, 24, FALSE) -> 2 | G3: 1 | H3: 100% Female | I3: F | J3: PV | K3: ='PV Regression Results'!$B$17+'PV Regression Results'!$B$18*'Pay Equity'!E3 -> 39642.658 | L3: =IF(K3>D3, K3-D3, 0) -> 0 | M3: =VLOOKUP(F3, 'Pay Structure'!$A$1:$D$12, 2, FALSE) -> 27935.261 | N3: =IF(K3>M3, L3, M3-D3) -> 0 | O3: Requires more experience than Admin Clerk
A4: Administrative Clerk | B4: Ops | C4: F | D4: 32008 | E4: 265 | F4: 2 | G4: 2 | H4: 100% Female | I4: F | J4: PV | K4: ='PV Regression Results'!$B$17+'PV Regression Results'!$B$18*'Pay Equity'!E4 -> 40381.692 | L4: =IF(K4>D4, K4-D4, 0) -> 8373.6922 | M4: =VLOOKUP(F4, 'Pay Structure'!$A$1:$D$12, 2, FALSE) -> 27935.261 | N4: =IF(K4>M4, L4, M4-D4) -> 8373.6922 | O4: Same job
A5: Administrative Clerk | B5: Ops | C5: F | D5: 36113 | E5: 265 | F5: 2 | G5: 2 | I5: F | J5: PV | K5: ='PV Regression Results'!$B$17+'PV Regression Results'!$B$18*'Pay Equity'!E5 -> 40381.692 | L5: =IF(K5>D5, K5-D5, 0) -> 4268.6922 | M5: =VLOOKUP(F5, 'Pay Structure'!$A$1:$D$12, 2, FALSE) -> 27935.261 | N5: =IF(K5>M5, L5, M5-D5) -> 4268.6922
A6: Circulation Technician & Receptionist | B6: Ops | C6: F | D6: 46481 | E6: =VLOOKUP(A6, Data!$A$2:$Z$46, 23, FALSE) -> 280 | F6: =VLOOKUP(A6, Data!$A$2:$Z$46, 24, FALSE) -> 3 | G6: 1 | H6: 100% Female | I6: F | J6: PV | K6: ='PV Regression Results'!$B$17+'PV Regression Results'!$B$18*'Pay Equity'!E6 -> 42598.795 | L6: =IF(K6>D6, K6-D6, 0) -> 0 | M6: =VLOOKUP(F6, 'Pay Structure'!$A$1:$D$12, 2, FALSE) -> 31287.492 | N6: =IF(K6>M6, L6, M6-D6) -> 0 | O6: Unique department
A7: Meetings and District Programs Coordinator | B7: Continuing Education | C7: F | D7: 42908 | E7: =VLOOKUP(A7, Data!$A$2:$Z$46, 23, FALSE) -> 280 | F7: =VLOOKUP(A7, Data!$A$2:$Z$46, 24, FALSE) -> 3 | G7: 2 | H7: 2/3 Female = 66.67% Female | I7: F | J7: PV | K7: ='PV Regression Results'!$B$17+'PV Regression Results'!$B$18*'Pay Equity'!E7 -> 42598.795 | L7: =IF(K7>D7, K7-D7, 0) -> 0 | M7: =VLOOKUP(F7, 'Pay Structure'!$A$1:$D$12, 2, FALSE) -> 31287.492 | N7: =IF(K7>M7, L7, M7-D7) -> 0 | O7: Same education and day to day job duties
A8: Seminar Coordinator | B8: Continuing Education | C8: M | D8: 37370 | E8: =VLOOKUP(A8, Data!$A$2:$Z$46, 23, FALSE) -> 280 | F8: =VLOOKUP(A8, Data!$A$2:$Z$46, 24, FALSE) -> 3 | G8: 2 | I8: F | J8: PV | K8: ='PV Regression Results'!$B$17+'PV Regression Results'!$B$18*'Pay Equity'!E8 -> 42598.795 | L8: =IF(K8>D8, K8-D8, 0) -> 5228.7949 | M8: =VLOOKUP(F8, 'Pay Structure'!$A$1:$D$12, 2, FALSE) -> 31287.492 | N8: =IF(K8>M8, L8, M8-D8) -> 5228.7949
A9: Seminar Coordinator | B9: Continuing Education | C9: F | D9: 38513 | E9: =VLOOKUP(A9, Data!$A$2:$Z$46, 23, FALSE) -> 280 | F9: =VLOOKUP(A9, Data!$A$2:$Z$46, 24, FALSE) -> 3 | G9: 2 | I9: F | J9: PV | K9: ='PV Regression Results'!$B$17+'PV Regression Results'!$B$18*'Pay Equity'!E9 -> 42598.795 | L9: =IF(K9>D9, K9-D9, 0) -> 4085.7949 | M9: =VLOOKUP(F9, 'Pay Structure'!$A$1:$D$12, 2, FALSE) -> 31287.492 | N9: =IF(K9>M9, L9, M9-D9) -> 4085.7949
A10: Secretary (Director Continuing Education) | B10: Continuing Education | C10: F | D10: 43898 | E10: =VLOOKUP(A10, Data!$A$2:$Z$46, 23, FALSE) -> 285 | F10: =VLOOKUP(A10, Data!$A$2:$Z$46, 24, FALSE) -> 3 | G10: 3 | H10: 100% Female | I10: F | J10: PV | K10: ='PV Regression Results'!$B$17+'PV Regression Results'!$B$18*'Pay Equity'!E10 -> 43337.829 | L10: =IF(K10>D10, K10-D10, 0) -> 0 | M10: =VLOOKUP(F10, 'Pay Structure'!$A$1:$D$12, 2, FALSE) -> 31287.492 | N10: =IF(K10>M10, L10, M10-D10) -> 0 | O10: Unique education requirement for department
A11: Administrative Assistant, Exec Office | B11: Exec | C11: F | D11: 37258 | E11: =VLOOKUP(A11, Data!$A$2:$Z$46, 23, FALSE) -> 290 | F11: =VLOOKUP(A11, Data!$A$2:$Z$46, 24, FALSE) -> 4 | G11: 1 | H11: 100% Female | I11: F | J11: Job to Job | K11: =D12 -> 41500 | L11: =IF(K11>D11, K11-D11, 0) -> 4242 | M11: =VLOOKUP(F11, 'Pay Structure'!$A$1:$D$12, 2, FALSE) -> 34416.242 | N11: =IF(K11>M11, L11, M11-D11) -> 4242 | O11: Unique department
A12: Junior Systems Administrator | B12: IT | C12: M | D12: 41500 | E12: =VLOOKUP(A12, Data!$A$2:$Z$46, 23, FALSE) -> 290 | F12: =VLOOKUP(A12, Data!$A$2:$Z$46, 24, FALSE) -> 4 | G12: 2 | H12: 100% Male | I12: M | J12: NA | K12: NA | L12: NA | M12: =VLOOKUP(F12, 'Pay Structure'!$A$1:$D$12, 2, FALSE) -> 34416.242 | N12: 0 | O12: Unique department
A13: Business Research Coordinator | B13: Ops | C13: F | D13: 58000 | E13: =VLOOKUP(A13, Data!$A$2:$Z$46, 23, FALSE) -> 295 | F13: =VLOOKUP(A13, Data!$A$2:$Z$46, 24, FALSE) -> 4 | G13: 3 | H13: 100% Female | I13: F | J13: Job to Job | K13: =D12 -> 41500 | L13: =IF(K13>D13, K13-D13, 0) -> 0 | M13: =VLOOKUP(F13, 'Pay Structure'!$A$1:$D$12, 2, FALSE) -> 34416.242 | N13: =IF(K13>M13, L13, M13-D13) -> 0 | O13: Unique education and experience requirements for department
A14: Junior Accountant | B14: Ops | C14: F | D14: 32810 | E14: =VLOOKUP(A14, Data!$A$2:$Z$46, 23, FALSE) -> 295 | F14: =VLOOKUP(A14, Data!$A$2:$Z$46, 24, FALSE) -> 4 | G14: 4 | H14: 100% Female | I14: F | J14: Job to Job | K14: =D12 -> 41500 | L14: =IF(K14>D14, K14-D14, 0) -> 8690 | M14: =VLOOKUP(F14, 'Pay Structure'!$A$1:$D$12, 2, FALSE) -> 34416.242 | N14: =IF(K14>M14, L14, M14-D14) -> 8690 | O14: Unique education requirement for department
A15: Administrative Clerk/mailroom clerk | B15: Ops | C15: F | D15: 40429 | E15: =VLOOKUP(A15, Data!$A$2:$Z$46, 23, FALSE) -> 310 | F15: =VLOOKUP(A15, Data!$A$2:$Z$46, 24, FALSE) -> 4 | G15: 5 | H15: 100% Female | I15: F | J15: Job to Job | K15: =D12 -> 41500 | L15: =IF(K15>D15, K15-D15, 0) -> 1071 | M15: =VLOOKUP(F15, 'Pay Structure'!$A$1:$D$12, 2, FALSE) -> 34416.242 | N15: =IF(K15>M15, L15, M15-D15) -> 1071 | O15: Unique education requirement for department
A16: Accountant | B16: Ops | C16: M | D16: 41530 | E16: =VLOOKUP(A16, Data!$A$2:$Z$46, 23, FALSE) -> 330 | F16: =VLOOKUP(A16, Data!$A$2:$Z$46, 24, FALSE) -> 5 | G16: 1 | H16: 100% Male | I16: M | J16: NA | K16: NA | L16: NA | M16: =VLOOKUP(F16, 'Pay Structure'!$A$1:$D$12, 2, FALSE) -> 38890.353 | N16: 0 | O16: Unique experience requirement for department
A17: Programmer | B17: IT | C17: M | D17: 77289 | E17: =VLOOKUP(A17, Data!$A$2:$Z$46, 23, FALSE) -> 335 | F17: =VLOOKUP(A17, Data!$A$2:$Z$46, 24, FALSE) -> 5 | G17: 2 | H17: 100% Male | I17: M | J17: NA | K17: NA | L17: NA | M17: =VLOOKUP(F17, 'Pay Structure'!$A$1:$D$12, 2, FALSE) -> 38890.353 | N17: 0 | O17: Unique department
A18: Career Consultant | B18: Ops | C18: F | D18: 68700 | E18: =VLOOKUP(A18, Data!$A$2:$Z$46, 23, FALSE) -> 340 | F18: =VLOOKUP(A18, Data!$A$2:$Z$46, 24, FALSE) -> 5 | G18: 3 | H18: 100% Female | I18: F | J18: Job to Job | K18: =D16 -> 41530 | L18: =IF(K18>D18, K18-D18, 0) -> 0 | M18: =VLOOKUP(F18, 'Pay Structure'!$A$1:$D$12, 2, FALSE) -> 38890.353 | N18: =IF(K18>M18, L18, M18-D18) -> 0 | O18: Unique job duties for department
A19: Associate Coordinator, Professional Programs | B19: Continuing Education | C19: F | D19: 39104 | E19: =VLOOKUP(A19, Data!$A$2:$Z$46, 23, FALSE) -> 345 | F19: =VLOOKUP(A19, Data!$A$2:$Z$46, 24, FALSE) -> 5 | G19: 4 | H19: 100% Female | I19: F | J19: Job to Job | K19: =D16 -> 41530 | L19: =IF(K19>D19, K19-D19, 0) -> 2426 | M19: =VLOOKUP(F19, 'Pay Structure'!$A$1:$D$12, 2, FALSE) -> 38890.353 | N19: =IF(K19>M19, L19, M19-D19) -> 2426 | O19: Unique department
A20: Business Analyst | B20: Ops | C20: M | D20: 63348 | E20: =VLOOKUP(A20, Data!$A$2:$Z$46, 23, FALSE) -> 350 | F20: =VLOOKUP(A20, Data!$A$2:$Z$46, 24, FALSE) -> 5 | G20: 5 | H20: 100% Male | I20: M | J20: NA | K20: NA | L20: NA | M20: =VLOOKUP(F20, 'Pay Structure'!$A$1:$D$12, 2, FALSE) -> 38890.353 | N20: 0 | O20: Unique experience requirement for department
A21: Secretary (Director Operations) | B21: Ops | C21: F | D21: 49508 | E21: =VLOOKUP(A21, Data!$A$2:$Z$46, 23, FALSE) -> 350 | F21: =VLOOKUP(A21, Data!$A$2:$Z$46, 24, FALSE) -> 5 | G21: 6 | H21: 100% Female | I21: F | J21: Job to Job | K21: =D16 -> 41530 | L21: =IF(K21>D21, K21-D21, 0) -> 0 | M21: =VLOOKUP(F21, 'Pay Structure'!$A$1:$D$12, 2, FALSE) -> 38890.353 | N21: =IF(K21>M21, L21, M21-D21) -> 0 | O21: Unique education and experience requirements for department
A22: Peer Review Administrator, Audit | B22: Quality Assurance | C22: F | D22: 54390 | E22: =VLOOKUP(A22, Data!$A$2:$Z$46, 23, FALSE) -> 355 | F22: =VLOOKUP(A22, Data!$A$2:$Z$46, 24, FALSE) -> 5 | G22: 7 | H22: 2/3 Male = 67% Male | I22: N | J22: NA | K22: NA | L22: NA | M22: =VLOOKUP(F22, 'Pay Structure'!$A$1:$D$12, 2, FALSE) -> 38890.353 | N22: 0 | O22: Same education and experience requirements and similar duties
A23: Peer Review Administrator, Audit | B23: Quality Assurance | C23: M | D23: 56000 | E23: =VLOOKUP(A23, Data!$A$2:$Z$46, 23, FALSE) -> 355 | F23: =VLOOKUP(A23, Data!$A$2:$Z$46, 24, FALSE) -> 5 | G23: 7 | I23: N | J23: NA | K23: NA | L23: NA | M23: =VLOOKUP(F23, 'Pay Structure'!$A$1:$D$12, 2, FALSE) -> 38890.353 | N23: 0
A24: Peer Review Administrator, Tax | B24: Quality Assurance | C24: M | D24: 58700 | E24: =VLOOKUP(A24, Data!$A$2:$Z$46, 23, FALSE) -> 360 | F24: =VLOOKUP(A24, Data!$A$2:$Z$46, 24, FALSE) -> 5 | G24: 7 | I24: N | J24: NA | K24: NA | L24: NA | M24: =VLOOKUP(F24, 'Pay Structure'!$A$1:$D$12, 2, FALSE) -> 38890.353 | N24: 0
A25: Information Officer | B25: Marketing | C25: F | D25: 55233 | E25: =VLOOKUP(A25, Data!$A$2:$Z$46, 23, FALSE) -> 365 | F25: =VLOOKUP(A25, Data!$A$2:$Z$46, 24, FALSE) -> 6 | G25: 1 | H25: 100% Female | I25: F | J25: Job to Job | K25: =D28 -> 51082 | L25: =IF(K25>D25, K25-D25, 0) -> 0 | M25: =VLOOKUP(F25, 'Pay Structure'!$A$1:$D$12, 2, FALSE) -> 43168.292 | N25: =IF(K25>M25, L25, M25-D25) -> 0 | O25: Unique education requirement for department
A26: Web Developer | B26: IT | C26: M | D26: 59000 | E26: =VLOOKUP(A26, Data!$A$2:$Z$46, 23, FALSE) -> 375 | F26: =VLOOKUP(A26, Data!$A$2:$Z$46, 24, FALSE) -> 6 | G26: 2 | H26: 100% Male | I26: M | J26: NA | K26: NA | L26: NA | M26: =VLOOKUP(F26, 'Pay Structure'!$A$1:$D$12, 2, FALSE) -> 43168.292 | N26: 0 | O26: Unique department
A27: Communications Specialist | B27: Marketing | C27: F | D27: 67040 | E27: =VLOOKUP(A27, Data!$A$2:$Z$46, 23, FALSE) -> 395 | F27: =VLOOKUP(A27, Data!$A$2:$Z$46, 24, FALSE) -> 6 | G27: 3 | H27: 100% Female | I27: F | J27: Job to Job | K27: =D28 -> 51082 | L27: =IF(K27>D27, K27-D27, 0) -> 0 | M27: =VLOOKUP(F27, 'Pay Structure'!$A$1:$D$12, 2, FALSE) -> 43168.292 | N27: =IF(K27>M27, L27, M27-D27) -> 0 | O27: Unique education requirement for department
A28: Senior Accountant | B28: Ops | C28: M | D28: 51082 | E28: =VLOOKUP(A28, Data!$A$2:$Z$46, 23, FALSE) -> 410 | F28: =VLOOKUP(A28, Data!$A$2:$Z$46, 24, FALSE) -> 6 | G28: 4 | H28: 100% Male | I28: M | J28: NA | K28: NA | L28: NA | M28: =VLOOKUP(F28, 'Pay Structure'!$A$1:$D$12, 2, FALSE) -> 43168.292 | N28: 0 | O28: Unique department
A29: Coordinator, Audit and Assurance | B29: Quality Assurance | C29: M | D29: 64755 | E29: =VLOOKUP(A29, Data!$A$2:$Z$46, 23, FALSE) -> 425 | F29: =VLOOKUP(A29, Data!$A$2:$Z$46, 24, FALSE) -> 7 | G29: 1 | H29: 100% Male | I29: M | J29: NA | K29: NA | L29: NA | M29: =VLOOKUP(F29, 'Pay Structure'!$A$1:$D$12, 2, FALSE) -> 44463.341 | N29: 0 | O29: Unique department
A30: Marketing Coordinator | B30: Marketing | C30: F | D30: 47375 | E30: =VLOOKUP(A30, Data!$A$2:$Z$46, 23, FALSE) -> 465 | F30: =VLOOKUP(A30, Data!$A$2:$Z$46, 24, FALSE) -> 7 | G30: 2 | H30: 100% Female | I30: F | J30: Job to Job | K30: =D29 -> 64755 | L30: =IF(K30>D30, K30-D30, 0) -> 17380 | M30: =VLOOKUP(F30, 'Pay Structure'!$A$1:$D$12, 2, FALSE) -> 44463.341 | N30: =IF(K30>M30, L30, M30-D30) -> 17380 | O30: Unique department
A31: Coordinator, Professional Programs | B31: Continuing Education | C31: F | D31: 53042 | E31: =VLOOKUP(A31, Data!$A$2:$Z$46, 23, FALSE) -> 525 | F31: =VLOOKUP(A31, Data!$A$2:$Z$46, 24, FALSE) -> 8 | G31: 1 | H31: 100% Female | I31: F | J31: Job to Job | K31: =D34 -> 69733 | L31: =IF(K31>D31, K31-D31, 0) -> 16691 | M31: =VLOOKUP(F31, 'Pay Structure'!$A$1:$D$12, 2, FALSE) -> 49354.308 | N31: =IF(K31>M31, L31, M31-D31) -> 16691 | O31: Unique education requirement for department
A32: Manager Conferences and Event Planning | B32: Continuing Education | C32: F | D32: 72180 | E32: =VLOOKUP(A32, Data!$A$2:$Z$46, 23, FALSE) -> 525 | F32: =VLOOKUP(A32, Data!$A$2:$Z$46, 24, FALSE) -> 8 | G32: 2 | H32: 100% Female | I32: F | J32: Job to Job | K32: =D34 -> 69733 | L32: =IF(K32>D32, K32-D32, 0) -> 0 | M32: =VLOOKUP(F32, 'Pay Structure'!$A$1:$D$12, 2, FALSE) -> 49354.308 | N32: =IF(K32>M32, L32, M32-D32) -> 0 | O32: Unique education requirement for department
A33: Manager, Workforce Recruitment | B33: Marketing | C33: M | D33: 83828 | E33: =VLOOKUP(A33, Data!$A$2:$Z$46, 23, FALSE) -> 545 | F33: =VLOOKUP(A33, Data!$A$2:$Z$46, 24, FALSE) -> 8 | G33: 3 | H33: 100% Male | I33: M | J33: NA | K33: NA | L33: NA | M33: =VLOOKUP(F33, 'Pay Structure'!$A$1:$D$12, 2, FALSE) -> 49354.308 | N33: 0 | O33: Unique job duties for department
A34: Manager Finance and Administration | B34: Ops | C34: M | D34: 69733 | E34: =VLOOKUP(A34, Data!$A$2:$Z$46, 23, FALSE) -> 565 | F34: =VLOOKUP(A34, Data!$A$2:$Z$46, 24, FALSE) -> 8 | G34: 4 | H34: 100% Male | I34: M | J34: NA | K34: NA | L34: NA | M34: =VLOOKUP(F34, 'Pay Structure'!$A$1:$D$12, 2, FALSE) -> 49354.308 | N34: 0 | O34: Unique department
A35: Manager, Education Outreach | B35: Marketing | C35: F | D35: 81247 | E35: =VLOOKUP(A35, Data!$A$2:$Z$46, 23, FALSE) -> 565 | F35: =VLOOKUP(A35, Data!$A$2:$Z$46, 24, FALSE) -> 8 | G35: 5 | H35: 100% Female | I35: F | J35: Job to Job | K35: =D34 -> 69733 | L35: =IF(K35>D35, K35-D35, 0) -> 0 | M35: =VLOOKUP(F35, 'Pay Structure'!$A$1:$D$12, 2, FALSE) -> 49354.308 | N35: =IF(K35>M35, L35, M35-D35) -> 0 | O35: Unique job duties for department
A36: Manager, Executive Office | B36: Exec | C36: F | D36: 71707 | E36: =VLOOKUP(A36, Data!$A$2:$Z$46, 23, FALSE) -> 650 | F36: =VLOOKUP(A36, Data!$A$2:$Z$46, 24, FALSE) -> 9 | G36: 1 | H36: 100% Female | I36: F | J36: Job to Job | K36: =D41 -> 83860 | L36: =IF(K36>D36, K36-D36, 0) -> 12153 | M36: =VLOOKUP(F36, 'Pay Structure'!$A$1:$D$12, 2, FALSE) -> 56757.454 | N36: =IF(K36>M36, L36, M36-D36) -> 12153 | O36: Unique department
A37: Manager, Audit and Assurance | B37: Quality Assurance | C37: M | D37: 84980 | E37: =VLOOKUP(A37, Data!$A$2:$Z$46, 23, FALSE) -> 655 | F37: =VLOOKUP(A37, Data!$A$2:$Z$46, 24, FALSE) -> 9 | G37: 2 | H37: 1/2 Female = 50% Female | I37: N | J37: NA | K37: NA | L37: NA | M37: =VLOOKUP(F37, 'Pay Structure'!$A$1:$D$12, 2, FALSE) -> 56757.454 | N37: 0 | O37: Same education and experience requirements and similar duties
A38: Manager, Tax Quality | B38: Quality Assurance | C38: F | D38: 70000 | E38: =VLOOKUP(A38, Data!$A$2:$Z$46, 23, FALSE) -> 655 | F38: =VLOOKUP(A38, Data!$A$2:$Z$46, 24, FALSE) -> 9 | G38: 2 | I38: N | J38: NA | K38: NA | L38: NA | M38: =VLOOKUP(F38, 'Pay Structure'!$A$1:$D$12, 2, FALSE) -> 56757.454 | N38: 0
A39: Manager, Member Services Centre | B39: Ops | C39: F | D39: 95151 | E39: =VLOOKUP(A39, Data!$A$2:$Z$46, 23, FALSE) -> 670 | F39: =VLOOKUP(A39, Data!$A$2:$Z$46, 24, FALSE) -> 9 | G39: 3 | H39: 100% Female | I39: F | J39: Job to Job | K39: =D41 -> 83860 | L39: =IF(K39>D39, K39-D39, 0) -> 0 | M39: =VLOOKUP(F39, 'Pay Structure'!$A$1:$D$12, 2, FALSE) -> 56757.454 | N39: =IF(K39>M39, L39, M39-D39) -> 0 | O39: Unique department
A40: Director, IT | B40: IT | C40: M | D40: 101981 | E40: =VLOOKUP(A40, Data!$A$2:$Z$46, 23, FALSE) -> 685 | F40: =VLOOKUP(A40, Data!$A$2:$Z$46, 24, FALSE) -> 9 | G40: 4 | H40: 100% Male | I40: M | J40: NA | K40: NA | L40: NA | M40: =VLOOKUP(F40, 'Pay Structure'!$A$1:$D$12, 2, FALSE) -> 56757.454 | N40: 0 | O40: Unique department
A41: Director, Continuing Education | B41: Continuing Education | C41: M | D41: 83860 | E41: =VLOOKUP(A41, Data!$A$2:$Z$46, 23, FALSE) -> 760 | F41: =VLOOKUP(A41, Data!$A$2:$Z$46, 24, FALSE) -> 9 | G41: 5 | H41: 100% Male | I41: M | J41: NA | K41: NA | L41: NA | M41: =VLOOKUP(F41, 'Pay Structure'!$A$1:$D$12, 2, FALSE) -> 56757.454 | N41: 0 | O41: Unique department
A42: Director, Quality Assurance | B42: Quality Assurance | C42: F | D42: 114302 | E42: =VLOOKUP(A42, Data!$A$2:$Z$46, 23, FALSE) -> 810 | F42: =VLOOKUP(A42, Data!$A$2:$Z$46, 24, FALSE) -> 10 | G42: 1 | H42: 100% Female | I42: F | J42: PV | K42: ='PV Regression Results'!$B$17+'PV Regression Results'!$B$18*'Pay Equity'!E42 -> 120936.43 | L42: =IF(K42>D42, K42-D42, 0) -> 6634.4255 | M42: =VLOOKUP(F42, 'Pay Structure'!$A$1:$D$12, 2, FALSE) -> 65271.073 | N42: =IF(K42>M42, L42, M42-D42) -> 6634.4255 | O42: Unique department
A43: Director, Marketing and Communications | B43: Marketing | C43: F | D43: 118571 | E43: =VLOOKUP(A43, Data!$A$2:$Z$46, 23, FALSE) -> 820 | F43: =VLOOKUP(A43, Data!$A$2:$Z$46, 24, FALSE) -> 10 | G43: 2 | H43: 100% Female | I43: F | J43: PV | K43: ='PV Regression Results'!$B$17+'PV Regression Results'!$B$18*'Pay Equity'!E43 -> 122414.49 | L43: =IF(K43>D43, K43-D43, 0) -> 3843.494 | M43: =VLOOKUP(F43, 'Pay Structure'!$A$1:$D$12, 2, FALSE) -> 65271.073 | N43: =IF(K43>M43, L43, M43-D43) -> 3843.494 | O43: Unique department
A44: Director, Operations | B44: Ops | C44: F | D44: 126947 | E44: =VLOOKUP(A44, Data!$A$2:$Z$46, 23, FALSE) -> 835 | F44: =VLOOKUP(A44, Data!$A$2:$Z$46, 24, FALSE) -> 10 | G44: 3 | H44: 100% Female | I44: F | J44: PV | K44: ='PV Regression Results'!$B$17+'PV Regression Results'!$B$18*'Pay Equity'!E44 -> 124631.6 | L44: =IF(K44>D44, K44-D44, 0) -> 0 | M44: =VLOOKUP(F44, 'Pay Structure'!$A$1:$D$12, 2, FALSE) -> 65271.073 | N44: =IF(K44>M44, L44, M44-D44) -> 0 | O44: Unique department
A45: Executive Director | B45: Exec | C45: M | D45: 171619 | E45: =VLOOKUP(A45, Data!$A$2:$Z$46, 23, FALSE) -> 985 | F45: =VLOOKUP(A45, Data!$A$2:$Z$46, 24, FALSE) -> 11 | G45: 1 | H45: 100% Male | I45: M | J45: NA | K45: NA | L45: NA | M45: =VLOOKUP(F45, 'Pay Structure'!$A$1:$D$12, 2, FALSE) -> 57739.795 | N45: 0 | O45: Unique

Sheet PV Regression Results
A1: SUMMARY OUTPUT
A3: Regression Statistics
A4: Multiple R | B4: 0.89326371
A5: R Square | B5: 0.79792006
A6: Adjusted R Square | B6: 0.77771207
A7: Standard Error | B7: 16551.333
A8: Observations | B8: 12
A10: ANOVA
B11: df | C11: SS | D11: MS | E11: F | F11: Significance F
A12: Regression | B12: 1 | C12: 1.0816883e+10 | D12: 1.0816883e+10 | E12: 39.485368 | F12: 9.0979653e-05
A13: Residual | B13: 10 | C13: 2.7394663e+09 | D13: 2.7394663e+08
A14: Total | B14: 11 | C14: 1.355635e+10
B16: Coefficients | C16: Standard Error | D16: t Stat | E16: P-value | F16: Lower 95% | G16: Upper 95% | H16: Lower 95.0% | I16: Upper 95.0%
A17: Intercept | B17: 1212.8769 | C17: 12794.489 | D17: 0.094796817 | E17: 0.92634886 | F17: -27295.022 | G17: 29720.776 | H17: -27295.022 | I17: 29720.776
A18: Total Points | B18: 147.80685 | C18: 23.52212 | D18: 6.2837384 | E18: 9.0979653e-05 | F18: 95.3963 | G18: 200.2174 | H18: 95.3963 | I18: 200.2174

Sheet PV Regression Data
A1: Position Title | B1: Department | C1: Gender | D1: 2007 Salary | E1: Total Points | F1: Gender of Class
A2: Junior Systems Administrator | B2: IT | C2: M | D2: 41500 | E2: =VLOOKUP(A2, Data!$A$2:$Z$46, 23, FALSE) -> 290 | F2: M
A3: Accountant | B3: Ops | C3: M | D3: 41530 | E3: =VLOOKUP(A3, Data!$A$2:$Z$46, 23, FALSE) -> 330 | F3: M
A4: Programmer | B4: IT | C4: M | D4: 77289 | E4: =VLOOKUP(A4, Data!$A$2:$Z$46, 23, FALSE) -> 335 | F4: M
A5: Business Analyst | B5: Ops | C5: M | D5: 63348 | E5: =VLOOKUP(A5, Data!$A$2:$Z$46, 23, FALSE) -> 350 | F5: M
A6: Web Developer | B6: IT | C6: M | D6: 59000 | E6: =VLOOKUP(A6, Data!$A$2:$Z$46, 23, FALSE) -> 375 | F6: M
A7: Senior Accountant | B7: Ops | C7: M | D7: 51082 | E7: =VLOOKUP(A7, Data!$A$2:$Z$46, 23, FALSE) -> 410 | F7: M
A8: Coordinator, Audit and Assurance | B8: Quality Assurance | C8: M | D8: 64755 | E8: =VLOOKUP(A8, Data!$A$2:$Z$46, 23, FALSE) -> 425 | F8: M
A9: Manager, Workforce Recruitment | B9: Marketing | C9: M | D9: 83828 | E9: =VLOOKUP(A9, Data!$A$2:$Z$46, 23, FALSE) -> 545 | F9: M
A10: Manager Finance and Administration | B10: Ops | C10: M | D10: 69733 | E10: =VLOOKUP(A10, Data!$A$2:$Z$46, 23, FALSE) -> 565 | F10: M
A11: Director, IT | B11: IT | C11: M | D11: 101981 | E11: 685 | F11: M
A12: Director, Continuing Education | B12: Continuing Education | C12: M | D12: 83860 | E12: 760 | F12: M
A13: Executive Director | B13: Exec | C13: M | D13: 171619 | E13: =VLOOKUP(A13, Data!$A$2:$Z$46, 23, FALSE) -> 985 | F13: M
